Workbook

Sheet Dashboard
A1: Big Books Company
B2: Income Statement | M2: Cash Flow Statement
C3: Actuals | F3: Forecast | N3: Actuals | Q3: Forecast
B4: ($ in Million Except Per Share Amounts) | C4: Historical 1 | D4: Historical 2 | E4: Historical 3 | F4: Forecast 1 | G4: Forecast 2 | H4: Forecast 3 | I4: Forecast 4 | J4: Forecast 5 | M4: ($ in Million Except Per Share Amounts) | N4: Historical 1 | O4: Historical 2 | P4: Historical 3 | Q4: Forecast 1 | R4: Forecast 2 | S4: Forecast 3 | T4: Forecast 4 | U4: Forecast 5
B5: Net Sales | C5: ='Income Statement'!C5 -> 2904.94 | D5: ='Income Statement'!D5 -> 3408 | E5: ='Income Statement'!E5 -> 3958.96 | F5: ='Income Statement'!F5 -> 4119.966 | G5: ='Income Statement'!G5 -> 4803.7718 | H5: ='Income Statement'!H5 -> 5602.8773 | I5: ='Income Statement'!I5 -> 6536.9387 | J5: ='Income Statement'!J5 -> 7628.9884 | M5: Operating Activities
B6: Cost of Sales | C6: ='Income Statement'!C6 -> 1494.8366 | D6: ='Income Statement'!D6 -> 1866.1246 | E6: ='Income Statement'!E6 -> 2309.7272 | F6: ='Income Statement'!F6 -> 2502.2446 | G6: ='Income Statement'!G6 -> 2916.6145 | H6: ='Income Statement'!H6 -> 3400.774 | I6: ='Income Statement'!I6 -> 3966.6171 | J6: ='Income Statement'!J6 -> 4628.0813 | M6: Net Income | O6: ='Cash Flow Statement'!D6 -> 754.10834 | P6: ='Cash Flow Statement'!E6 -> 740.30492 | Q6: ='Cash Flow Statement'!F6 -> 695.99587 | R6: ='Cash Flow Statement'!G6 -> 829.82064 | S6: ='Cash Flow Statement'!H6 -> 988.81888 | T6: ='Cash Flow Statement'!I6 -> 1173.3315 | U6: ='Cash Flow Statement'!J6 -> 1387.8812
B7: Gross Profit | C7: ='Income Statement'!C7 -> 1410.1034 | D7: ='Income Statement'!D7 -> 1541.8754 | E7: ='Income Statement'!E7 -> 1649.2328 | F7: ='Income Statement'!F7 -> 1617.7214 | G7: ='Income Statement'!G7 -> 1887.1573 | H7: ='Income Statement'!H7 -> 2202.1033 | I7: ='Income Statement'!I7 -> 2570.3216 | J7: ='Income Statement'!J7 -> 3000.9071 | M7: Depreciation | O7: ='Cash Flow Statement'!D7 -> 123.1 | P7: ='Cash Flow Statement'!E7 -> 140 | Q7: ='Cash Flow Statement'!F7 -> 151.53313 | R7: ='Cash Flow Statement'!G7 -> 179.55514 | S7: ='Cash Flow Statement'!H7 -> 212.23859 | T7: ='Cash Flow Statement'!I7 -> 250.37073 | U7: ='Cash Flow Statement'!J7 -> 294.87316
M8: Amortization | O8: ='Cash Flow Statement'!D8 -> 10.666 | P8: ='Cash Flow Statement'!E8 -> 13.035 | Q8: ='Cash Flow Statement'!F8 -> 13.295973 | R8: ='Cash Flow Statement'!G8 -> 17.13899 | S8: ='Cash Flow Statement'!H8 -> 21.621292 | T8: ='Cash Flow Statement'!I8 -> 26.850843 | U8: ='Cash Flow Statement'!J8 -> 32.954034
B9: Selling, General & Admin Costs | C9: ='Income Statement'!C9 -> 305.14255 | D9: ='Income Statement'!D9 -> 388.2872 | E9: ='Income Statement'!E9 -> 448.0675 | F9: ='Income Statement'!F9 -> 463.83868 | G9: ='Income Statement'!G9 -> 540.94103 | H9: ='Income Statement'!H9 -> 631.05976 | I9: ='Income Statement'!I9 -> 736.41607 | J9: ='Income Statement'!J9 -> 859.61298 | M9: Change in Working Capital | O9: ='Cash Flow Statement'!D9 -> 0 | P9: ='Cash Flow Statement'!E9 -> 0 | Q9: ='Cash Flow Statement'!F9 -> 0 | R9: ='Cash Flow Statement'!G9 -> 0 | S9: ='Cash Flow Statement'!H9 -> 0 | T9: ='Cash Flow Statement'!I9 -> 0 | U9: ='Cash Flow Statement'!J9 -> 0
B10: EBITDA | C10: ='Income Statement'!C10 -> 1104.9608 | D10: ='Income Statement'!D10 -> 1153.5882 | E10: ='Income Statement'!E10 -> 1201.1653 | F10: ='Income Statement'!F10 -> 1153.8827 | G10: ='Income Statement'!G10 -> 1346.2162 | H10: ='Income Statement'!H10 -> 1571.0435 | I10: ='Income Statement'!I10 -> 1833.9055 | J10: ='Income Statement'!J10 -> 2141.2941 | M10: Change in Assets & Liabilities (if any) | O10: ='Cash Flow Statement'!D16 -> -14 | P10: ='Cash Flow Statement'!E16 -> 36 | Q10: ='Cash Flow Statement'!F16 -> 0 | R10: ='Cash Flow Statement'!G16 -> 0 | S10: ='Cash Flow Statement'!H16 -> 0 | T10: ='Cash Flow Statement'!I16 -> 0 | U10: ='Cash Flow Statement'!J16 -> 0
M11: Cash Flow from Operating Activities | O11: ='Cash Flow Statement'!D17 -> 834.57434 | P11: ='Cash Flow Statement'!E17 -> 987.83992 | Q11: ='Cash Flow Statement'!F17 -> 891.97354 | R11: ='Cash Flow Statement'!G17 -> 964.77779 | S11: ='Cash Flow Statement'!H17 -> 1150.5262 | T11: ='Cash Flow Statement'!I17 -> 1366.2089 | U11: ='Cash Flow Statement'!J17 -> 1617.0918
B12: Depreciation | C12: ='Income Statement'!C12 -> 101.9 | D12: ='Income Statement'!D12 -> 123.1 | E12: ='Income Statement'!E12 -> 140 | F12: ='Income Statement'!F12 -> 151.53313 | G12: ='Income Statement'!G12 -> 179.55514 | H12: ='Income Statement'!H12 -> 212.23859 | I12: ='Income Statement'!I12 -> 250.37073 | J12: ='Income Statement'!J12 -> 294.87316 | O12: ='Cash Flow Statement'!D18 -> 0 | P12: ='Cash Flow Statement'!E18 -> 0 | Q12: ='Cash Flow Statement'!F18 -> 0 | R12: ='Cash Flow Statement'!G18 -> 0 | S12: ='Cash Flow Statement'!H18 -> 0 | T12: ='Cash Flow Statement'!I18 -> 0 | U12: ='Cash Flow Statement'!J18 -> 0
B13: Amortization | C13: ='Income Statement'!C13 -> 9.367 | D13: ='Income Statement'!D13 -> 10.666 | E13: ='Income Statement'!E13 -> 13.035 | F13: ='Income Statement'!F13 -> 13.295973 | G13: ='Income Statement'!G13 -> 17.13899 | H13: ='Income Statement'!H13 -> 21.621292 | I13: ='Income Statement'!I13 -> 26.850843 | J13: ='Income Statement'!J13 -> 32.954034 | M13: Investment Activities | O13: ='Cash Flow Statement'!D19 -> 0 | P13: ='Cash Flow Statement'!E19 -> 0 | Q13: ='Cash Flow Statement'!F19 -> 0 | R13: ='Cash Flow Statement'!G19 -> 0 | S13: ='Cash Flow Statement'!H19 -> 0 | T13: ='Cash Flow Statement'!I19 -> 0 | U13: ='Cash Flow Statement'!J19 -> 0
B14: EBIT | C14: ='Income Statement'!C14 -> 993.69382 | D14: ='Income Statement'!D14 -> 1019.8222 | E14: ='Income Statement'!E14 -> 1048.1303 | F14: ='Income Statement'!F14 -> 989.05358 | G14: ='Income Statement'!G14 -> 1149.5221 | H14: ='Income Statement'!H14 -> 1337.1836 | I14: ='Income Statement'!I14 -> 1556.684 | J14: ='Income Statement'!J14 -> 1813.4669 | M14: Purchase of Marketable Securities | O14: ='Cash Flow Statement'!D20 -> -10 | P14: ='Cash Flow Statement'!E20 -> -10 | Q14: ='Cash Flow Statement'!F20 -> -10 | R14: ='Cash Flow Statement'!G20 -> -10 | S14: ='Cash Flow Statement'!H20 -> -10 | T14: ='Cash Flow Statement'!I20 -> -10 | U14: ='Cash Flow Statement'!J20 -> -10
M15: Purchase of Long Term Securities | O15: ='Cash Flow Statement'!D21 -> -20 | P15: ='Cash Flow Statement'!E21 -> -20 | Q15: ='Cash Flow Statement'!F21 -> -20 | R15: ='Cash Flow Statement'!G21 -> -20 | S15: ='Cash Flow Statement'!H21 -> -20 | T15: ='Cash Flow Statement'!I21 -> -20 | U15: ='Cash Flow Statement'!J21 -> -20
B16: Interest Expense | C16: ='Income Statement'!C16 -> 44.10772 | D16: ='Income Statement'!D16 -> 60.11464 | E16: ='Income Statement'!E16 -> 63.765 | F16: ='Income Statement'!F16 -> 73.105859 | G16: ='Income Statement'!G16 -> 62.785391 | H16: ='Income Statement'!H16 -> 52.279533 | I16: ='Income Statement'!I16 -> 45.45 | J16: ='Income Statement'!J16 -> 43.2 | M16: Capital Expenditures | O16: ='Cash Flow Statement'!D22 -> -145 | P16: ='Cash Flow Statement'!E22 -> -250 | Q16: ='Cash Flow Statement'!F22 -> -288.39762 | R16: ='Cash Flow Statement'!G22 -> -336.26403 | S16: ='Cash Flow Statement'!H22 -> -392.20141 | T16: ='Cash Flow Statement'!I22 -> -457.58571 | U16: ='Cash Flow Statement'!J22 -> -534.02919
B17: Interest Income | C17: ='Income Statement'!C17 -> 0 | D17: ='Income Statement'!D17 -> 9.4007832 | E17: ='Income Statement'!E17 -> 10.939602 | F17: ='Income Statement'!F17 -> 11.002482 | G17: ='Income Statement'!G17 -> 11.176884 | H17: ='Income Statement'!H17 -> 13.793676 | I17: ='Income Statement'!I17 -> 22.634329 | J17: ='Income Statement'!J17 -> 36.809235 | M17: Additions to Intangibles | O17: ='Cash Flow Statement'!D23 -> -26.466 | P17: ='Cash Flow Statement'!E23 -> -30.735 | Q17: ='Cash Flow Statement'!F23 -> -32.959728 | R17: ='Cash Flow Statement'!G23 -> -38.430174 | S17: ='Cash Flow Statement'!H23 -> -44.823018 | T17: ='Cash Flow Statement'!I23 -> -52.295509 | U17: ='Cash Flow Statement'!J23 -> -61.031907
B18: Pretax Income | C18: ='Income Statement'!C18 -> 949.5861 | D18: ='Income Statement'!D18 -> 969.10834 | E18: ='Income Statement'!E18 -> 995.30492 | F18: ='Income Statement'!F18 -> 926.9502 | G18: ='Income Statement'!G18 -> 1097.9136 | H18: ='Income Statement'!H18 -> 1298.6978 | I18: ='Income Statement'!I18 -> 1533.8683 | J18: ='Income Statement'!J18 -> 1807.0762 | M18: Cash Flow from Investing Activities | O18: ='Cash Flow Statement'!D24 -> -201.466 | P18: ='Cash Flow Statement'!E24 -> -310.735 | Q18: ='Cash Flow Statement'!F24 -> -351.35735 | R18: ='Cash Flow Statement'!G24 -> -404.6942 | S18: ='Cash Flow Statement'!H24 -> -467.02443 | T18: ='Cash Flow Statement'!I24 -> -539.88122 | U18: ='Cash Flow Statement'!J24 -> -625.06109
O19: ='Cash Flow Statement'!D25 -> 0 | P19: ='Cash Flow Statement'!E25 -> 0 | Q19: ='Cash Flow Statement'!F25 -> 0 | R19: ='Cash Flow Statement'!G25 -> 0 | S19: ='Cash Flow Statement'!H25 -> 0 | T19: ='Cash Flow Statement'!I25 -> 0 | U19: ='Cash Flow Statement'!J25 -> 0
B20: Income Taxes | C20: ='Income Statement'!C20 -> 175 | D20: ='Income Statement'!D20 -> 215 | E20: ='Income Statement'!E20 -> 255 | F20: ='Income Statement'!F20 -> 231.73755 | G20: ='Income Statement'!G20 -> 274.4784 | H20: ='Income Statement'!H20 -> 324.67445 | I20: ='Income Statement'!I20 -> 383.46707 | J20: ='Income Statement'!J20 -> 451.76904 | M20: Financing Activities | O20: ='Cash Flow Statement'!D26 -> 0 | P20: ='Cash Flow Statement'!E26 -> 0 | Q20: ='Cash Flow Statement'!F26 -> 0 | R20: ='Cash Flow Statement'!G26 -> 0 | S20: ='Cash Flow Statement'!H26 -> 0 | T20: ='Cash Flow Statement'!I26 -> 0 | U20: ='Cash Flow Statement'!J26 -> 0
B21: Net Income | C21: ='Income Statement'!C21 -> 774.5861 | D21: ='Income Statement'!D21 -> 754.10834 | E21: ='Income Statement'!E21 -> 740.30492 | F21: ='Income Statement'!F21 -> 695.21265 | G21: ='Income Statement'!G21 -> 823.4352 | H21: ='Income Statement'!H21 -> 974.02334 | I21: ='Income Statement'!I21 -> 1150.4012 | J21: ='Income Statement'!J21 -> 1355.3071 | M21: Proceeds from/ (repayment of) Revolving Credit Facility | O21: ='Cash Flow Statement'!D27 -> -100 | P21: ='Cash Flow Statement'!E27 -> -49 | Q21: ='Cash Flow Statement'!F27 -> 49.4693 | R21: ='Cash Flow Statement'!G27 -> -42.458335 | S21: ='Cash Flow Statement'!H27 -> -66.004154 | T21: ='Cash Flow Statement'!I27 -> 0 | U21: ='Cash Flow Statement'!J27 -> 0
M22: Issuance of Long Term Debt | O22: ='Cash Flow Statement'!D28 -> 0 | P22: ='Cash Flow Statement'!E28 -> 0 | Q22: ='Cash Flow Statement'!F28 -> 0 | R22: ='Cash Flow Statement'!G28 -> 0 | S22: ='Cash Flow Statement'!H28 -> 0 | T22: ='Cash Flow Statement'!I28 -> 0 | U22: ='Cash Flow Statement'!J28 -> 0
M23: (Repayment) of Long Term Debt | O23: ='Cash Flow Statement'!D29 -> -210 | P23: ='Cash Flow Statement'!E29 -> -355 | Q23: ='Cash Flow Statement'!F29 -> -300 | R23: ='Cash Flow Statement'!G29 -> -200 | S23: ='Cash Flow Statement'!H29 -> -100 | T23: ='Cash Flow Statement'!I29 -> -50 | U23: ='Cash Flow Statement'!J29 -> -50
B24: Outstanding Shares | C24: ='Income Statement'!C24 -> 99.245 | D24: ='Income Statement'!D24 -> 97.995 | E24: ='Income Statement'!E24 -> 96.61569 | F24: ='Income Statement'!F24 -> 94.909212 | G24: ='Income Statement'!G24 -> 93.490005 | H24: ='Income Statement'!H24 -> 92.305415 | I24: ='Income Statement'!I24 -> 91.313227 | J24: ='Income Statement'!J24 -> 90.478741 | M24: Issuance/ (Repurchase of) Equity | O24: ='Cash Flow Statement'!D30 -> -75 | P24: ='Cash Flow Statement'!E30 -> -80 | Q24: ='Cash Flow Statement'!F30 -> -100 | R24: ='Cash Flow Statement'!G30 -> -100 | S24: ='Cash Flow Statement'!H30 -> -100 | T24: ='Cash Flow Statement'!I30 -> -100 | U24: ='Cash Flow Statement'!J30 -> -100
B25: EPS | C25: ='Income Statement'!C26 -> 7.8047872 | D25: ='Income Statement'!D26 -> 7.6953757 | E25: ='Income Statement'!E26 -> 7.6623675 | F25: ='Income Statement'!F26 -> 7.325029 | G25: ='Income Statement'!G26 -> 8.8077357 | H25: ='Income Statement'!H26 -> 10.55218 | I25: ='Income Statement'!I26 -> 12.598408 | J25: ='Income Statement'!J26 -> 14.979288 | M25: Dividends | O25: ='Cash Flow Statement'!D31 -> -190 | P25: ='Cash Flow Statement'!E31 -> -230 | Q25: ='Cash Flow Statement'!F31 -> -208.79876 | R25: ='Cash Flow Statement'!G31 -> -248.94619 | S25: ='Cash Flow Statement'!H31 -> -296.64566 | T25: ='Cash Flow Statement'!I31 -> -351.99945 | U25: ='Cash Flow Statement'!J31 -> -416.36436
M26: Cash Flow from Financing Activities | O26: ='Cash Flow Statement'!D32 -> -575 | P26: ='Cash Flow Statement'!E32 -> -714 | Q26: ='Cash Flow Statement'!F32 -> -559.32946 | R26: ='Cash Flow Statement'!G32 -> -591.40453 | S26: ='Cash Flow Statement'!H32 -> -562.64982 | T26: ='Cash Flow Statement'!I32 -> -501.99945 | U26: ='Cash Flow Statement'!J32 -> -566.36436
O27: ='Cash Flow Statement'!D33 -> 0 | P27: ='Cash Flow Statement'!E33 -> 0 | Q27: ='Cash Flow Statement'!F33 -> 0 | R27: ='Cash Flow Statement'!G33 -> 0 | S27: ='Cash Flow Statement'!H33 -> 0 | T27: ='Cash Flow Statement'!I33 -> 0 | U27: ='Cash Flow Statement'!J33 -> 0
B28: Balance Sheet | M28: Net Change in Cash | O28: ='Cash Flow Statement'!D34 -> 58.108342 | P28: ='Cash Flow Statement'!E34 -> -36.895075 | Q28: ='Cash Flow Statement'!F34 -> -18.713267 | R28: ='Cash Flow Statement'!G34 -> -31.32094 | S28: ='Cash Flow Statement'!H34 -> 120.85192 | T28: ='Cash Flow Statement'!I34 -> 324.32827 | U28: ='Cash Flow Statement'!J34 -> 425.66635
C29: Actuals | F29: Forecast | M29: Beginning Cash Balance | O29: ='Cash Flow Statement'!D35 -> 27.5 | P29: ='Cash Flow Statement'!E35 -> 85.608342 | Q29: ='Cash Flow Statement'!F35 -> 48.713267 | R29: ='Cash Flow Statement'!G35 -> 30 | S29: ='Cash Flow Statement'!H35 -> -1.3209401 | T29: ='Cash Flow Statement'!I35 -> 119.53098 | U29: ='Cash Flow Statement'!J35 -> 443.85925
B30: ($ in Million Except Per Share Amounts) | C30: Historical 1 | D30: Historical 2 | E30: Historical 3 | F30: Forecast 1 | G30: Forecast 2 | H30: Forecast 3 | I30: Forecast 4 | J30: Forecast 5 | M30: Ending Cash Balance | N30: ='Cash Flow Statement'!C36 -> 27.5 | O30: ='Cash Flow Statement'!D36 -> 85.608342 | P30: ='Cash Flow Statement'!E36 -> 48.713267 | Q30: ='Cash Flow Statement'!F36 -> 30 | R30: ='Cash Flow Statement'!G36 -> -1.3209401 | S30: ='Cash Flow Statement'!H36 -> 119.53098 | T30: ='Cash Flow Statement'!I36 -> 443.85925 | U30: ='Cash Flow Statement'!J36 -> 869.5256
B32: Current Assets
B33: Cash & Cash Equivalents | C33: ='Balance Sheet'!C7 -> 27.5 | D33: ='Balance Sheet'!D7 -> 85.608342 | E33: ='Balance Sheet'!E7 -> 48.713267 | F33: ='Balance Sheet'!F7 -> 30 | G33: ='Balance Sheet'!G7 -> -1.3209401 | H33: ='Balance Sheet'!H7 -> 119.53098 | I33: ='Balance Sheet'!I7 -> 443.85925 | J33: ='Balance Sheet'!J7 -> 869.5256
B34: Marketable Securities | C34: ='Balance Sheet'!C8 -> 40 | D34: ='Balance Sheet'!D8 -> 50 | E34: ='Balance Sheet'!E8 -> 60 | F34: ='Balance Sheet'!F8 -> 70 | G34: ='Balance Sheet'!G8 -> 80 | H34: ='Balance Sheet'!H8 -> 90 | I34: ='Balance Sheet'!I8 -> 100 | J34: ='Balance Sheet'!J8 -> 110
B35: Receivables | C35: ='Balance Sheet'!C9 -> 462.9 | D35: ='Balance Sheet'!D9 -> 473.7 | E35: ='Balance Sheet'!E9 -> 473 | F35: ='Balance Sheet'!F9 -> 474.07828 | G35: ='Balance Sheet'!G9 -> 552.76278 | H35: ='Balance Sheet'!H9 -> 644.71465 | I35: ='Balance Sheet'!I9 -> 752.19568 | J35: ='Balance Sheet'!J9 -> 877.8562
B36: Inventory | C36: ='Balance Sheet'!C10 -> 327 | D36: ='Balance Sheet'!D10 -> 350.2 | E36: ='Balance Sheet'!E10 -> 383.8 | F36: ='Balance Sheet'!F10 -> 411.32788 | G36: ='Balance Sheet'!G10 -> 479.44348 | H36: ='Balance Sheet'!H10 -> 559.03134 | I36: ='Balance Sheet'!I10 -> 652.04664 | J36: ='Balance Sheet'!J10 -> 760.78048
B37: Other Current Assets | C37: ='Balance Sheet'!C11 -> 87.4 | D37: ='Balance Sheet'!D11 -> 82.8 | E37: ='Balance Sheet'!E11 -> 83.5 | F37: ='Balance Sheet'!F11 -> 82.39932 | G37: ='Balance Sheet'!G11 -> 96.075436 | H37: ='Balance Sheet'!H11 -> 112.05755 | I37: ='Balance Sheet'!I11 -> 130.73877 | J37: ='Balance Sheet'!J11 -> 152.57977
B38: Total Current Assets | C38: ='Balance Sheet'!C12 -> 944.8 | D38: ='Balance Sheet'!D12 -> 1042.3083 | E38: ='Balance Sheet'!E12 -> 1049.0133 | F38: ='Balance Sheet'!F12 -> 1067.8055 | G38: ='Balance Sheet'!G12 -> 1206.9608 | H38: ='Balance Sheet'!H12 -> 1525.3345 | I38: ='Balance Sheet'!I12 -> 2078.8403 | J38: ='Balance Sheet'!J12 -> 2770.742
B40: Long Term Securities | C40: ='Balance Sheet'!C14 -> 160 | D40: ='Balance Sheet'!D14 -> 180 | E40: ='Balance Sheet'!E14 -> 200 | F40: ='Balance Sheet'!F14 -> 220 | G40: ='Balance Sheet'!G14 -> 240 | H40: ='Balance Sheet'!H14 -> 260 | I40: ='Balance Sheet'!I14 -> 280 | J40: ='Balance Sheet'!J14 -> 300
B42: Land | C42: ='Balance Sheet'!C16 -> 30 | D42: ='Balance Sheet'!D16 -> 30 | E42: ='Balance Sheet'!E16 -> 30 | F42: ='Balance Sheet'!F16 -> 30 | G42: ='Balance Sheet'!G16 -> 30 | H42: ='Balance Sheet'!H16 -> 30 | I42: ='Balance Sheet'!I16 -> 30 | J42: ='Balance Sheet'!J16 -> 30
B43: Machinery and equipment | C43: ='Balance Sheet'!C17 -> 630 | D43: ='Balance Sheet'!D17 -> 700 | E43: ='Balance Sheet'!E17 -> 875 | F43: ='Balance Sheet'!F17 -> 1080.9983 | G43: ='Balance Sheet'!G17 -> 1321.1869 | H43: ='Balance Sheet'!H17 -> 1601.3308 | I43: ='Balance Sheet'!I17 -> 1928.1777 | J43: ='Balance Sheet'!J17 -> 2309.6271
B44: Automobiles and trucks | C44: ='Balance Sheet'!C18 -> 250 | D44: ='Balance Sheet'!D18 -> 325 | E44: ='Balance Sheet'!E18 -> 400 | F44: ='Balance Sheet'!F18 -> 482.39932 | G44: ='Balance Sheet'!G18 -> 578.47476 | H44: ='Balance Sheet'!H18 -> 690.5323 | I44: ='Balance Sheet'!I18 -> 821.27107 | J44: ='Balance Sheet'!J18 -> 973.85084
B45: Gross PPE | C45: ='Balance Sheet'!C19 -> 910 | D45: ='Balance Sheet'!D19 -> 1055 | E45: ='Balance Sheet'!E19 -> 1305 | F45: ='Balance Sheet'!F19 -> 1593.3976 | G45: ='Balance Sheet'!G19 -> 1929.6616 | H45: ='Balance Sheet'!H19 -> 2321.8631 | I45: ='Balance Sheet'!I19 -> 2779.4488 | J45: ='Balance Sheet'!J19 -> 3313.4779
B46: Accumulated Depreciation | C46: ='Balance Sheet'!C20 -> -101.9 | D46: ='Balance Sheet'!D20 -> -225 | E46: ='Balance Sheet'!E20 -> -365 | F46: ='Balance Sheet'!F20 -> -516.53313 | G46: ='Balance Sheet'!G20 -> -696.08827 | H46: ='Balance Sheet'!H20 -> -908.32686 | I46: ='Balance Sheet'!I20 -> -1158.6976 | J46: ='Balance Sheet'!J20 -> -1453.5708
B47: Net PPE | C47: ='Balance Sheet'!C21 -> 808.1 | D47: ='Balance Sheet'!D21 -> 830 | E47: ='Balance Sheet'!E21 -> 940 | F47: ='Balance Sheet'!F21 -> 1076.8645 | G47: ='Balance Sheet'!G21 -> 1233.5734 | H47: ='Balance Sheet'!H21 -> 1413.5362 | I47: ='Balance Sheet'!I21 -> 1620.7512 | J47: ='Balance Sheet'!J21 -> 1859.9072
C48: ='Balance Sheet'!C22 -> 0 | D48: ='Balance Sheet'!D22 -> 0 | E48: ='Balance Sheet'!E22 -> 0 | F48: ='Balance Sheet'!F22 -> 0 | G48: ='Balance Sheet'!G22 -> 0 | H48: ='Balance Sheet'!H22 -> 0 | I48: ='Balance Sheet'!I22 -> 0 | J48: ='Balance Sheet'!J22 -> 0
B49: Other Assets | C49: ='Balance Sheet'!C23 -> 0 | D49: ='Balance Sheet'!D23 -> 0 | E49: ='Balance Sheet'!E23 -> 0 | F49: ='Balance Sheet'!F23 -> 0 | G49: ='Balance Sheet'!G23 -> 0 | H49: ='Balance Sheet'!H23 -> 0 | I49: ='Balance Sheet'!I23 -> 0 | J49: ='Balance Sheet'!J23 -> 0
B50: Intangibles, net | C50: ='Balance Sheet'!C24 -> 46.5 | D50: ='Balance Sheet'!D24 -> 62.3 | E50: ='Balance Sheet'!E24 -> 80 | F50: ='Balance Sheet'!F24 -> 99.663755 | G50: ='Balance Sheet'!G24 -> 120.95494 | H50: ='Balance Sheet'!H24 -> 144.15667 | I50: ='Balance Sheet'!I24 -> 169.60133 | J50: ='Balance Sheet'!J24 -> 197.67921
B51: Goodwill | C51: ='Balance Sheet'!C25 -> 1671.7 | D51: ='Balance Sheet'!D25 -> 1671.7 | E51: ='Balance Sheet'!E25 -> 1671.7 | F51: ='Balance Sheet'!F25 -> 1671.7 | G51: ='Balance Sheet'!G25 -> 1671.7 | H51: ='Balance Sheet'!H25 -> 1671.7 | I51: ='Balance Sheet'!I25 -> 1671.7 | J51: ='Balance Sheet'!J25 -> 1671.7
B53: Total Assets | C53: ='Balance Sheet'!C27 -> 3631.1 | D53: ='Balance Sheet'!D27 -> 3786.3083 | E53: ='Balance Sheet'!E27 -> 3940.7133 | F53: ='Balance Sheet'!F27 -> 4136.0337 | G53: ='Balance Sheet'!G27 -> 4473.1891 | H53: ='Balance Sheet'!H27 -> 5014.7274 | I53: ='Balance Sheet'!I27 -> 5820.8928 | J53: ='Balance Sheet'!J27 -> 6800.0284
B55: Current Liabilities | C55: ='Balance Sheet'!C29 -> 0 | D55: ='Balance Sheet'!D29 -> 0 | E55: ='Balance Sheet'!E29 -> 0 | F55: ='Balance Sheet'!F29 -> 0 | G55: ='Balance Sheet'!G29 -> 0 | H55: ='Balance Sheet'!H29 -> 0 | I55: ='Balance Sheet'!I29 -> 0 | J55: ='Balance Sheet'!J29 -> 0
B56: Accounts Payable | C56: ='Balance Sheet'!C30 -> 206.4 | D56: ='Balance Sheet'!D30 -> 221.4 | E56: ='Balance Sheet'!E30 -> 279.1 | F56: ='Balance Sheet'!F30 -> 308.49591 | G56: ='Balance Sheet'!G30 -> 359.58261 | H56: ='Balance Sheet'!H30 -> 419.27351 | I56: ='Balance Sheet'!I30 -> 489.03498 | J56: ='Balance Sheet'!J30 -> 570.58536
B57: Accrued Liabilities | C57: ='Balance Sheet'!C31 -> 180.7 | D57: ='Balance Sheet'!D31 -> 161.3 | E57: ='Balance Sheet'!E31 -> 176.7 | F57: ='Balance Sheet'!F31 -> 200.17957 | G57: ='Balance Sheet'!G31 -> 233.32916 | H57: ='Balance Sheet'!H31 -> 272.06192 | I57: ='Balance Sheet'!I31 -> 317.32937 | J57: ='Balance Sheet'!J31 -> 370.2465
B58: Other Current Liabilities | C58: ='Balance Sheet'!C32 -> 68.3 | D58: ='Balance Sheet'!D32 -> 62.8 | E58: ='Balance Sheet'!E32 -> 81.8 | F58: ='Balance Sheet'!F32 -> 87.578562 | G58: ='Balance Sheet'!G32 -> 102.08151 | H58: ='Balance Sheet'!H32 -> 119.02709 | I58: ='Balance Sheet'!I32 -> 138.8316 | J58: ='Balance Sheet'!J32 -> 161.98284
B59: Total Current Liabilities | C59: ='Balance Sheet'!C33 -> 455.4 | D59: ='Balance Sheet'!D33 -> 445.5 | E59: ='Balance Sheet'!E33 -> 537.6 | F59: ='Balance Sheet'!F33 -> 596.25405 | G59: ='Balance Sheet'!G33 -> 694.99328 | H59: ='Balance Sheet'!H33 -> 810.36252 | I59: ='Balance Sheet'!I33 -> 945.19594 | J59: ='Balance Sheet'!J33 -> 1102.8147
B61: Loan Funds
B62: Revolving Credit Facility | C62: ='Balance Sheet'!C36 -> 250 | D62: ='Balance Sheet'!D36 -> 150 | E62: ='Balance Sheet'!E36 -> 101 | F62: ='Balance Sheet'!F36 -> 150.4693 | G62: ='Balance Sheet'!G36 -> 138.18131 | H62: ='Balance Sheet'!H36 -> 0 | I62: ='Balance Sheet'!I36 -> 0 | J62: ='Balance Sheet'!J36 -> 0
B63: Long Term Debt | C63: ='Balance Sheet'!C37 -> 2200 | D63: ='Balance Sheet'!D37 -> 1990 | E63: ='Balance Sheet'!E37 -> 1635 | F63: ='Balance Sheet'!F37 -> 1335 | G63: ='Balance Sheet'!G37 -> 1135 | H63: ='Balance Sheet'!H37 -> 1035 | I63: ='Balance Sheet'!I37 -> 985 | J63: ='Balance Sheet'!J37 -> 935
B64: Total Loan Funds | C64: ='Balance Sheet'!C38 -> 2450 | D64: ='Balance Sheet'!D38 -> 2140 | E64: ='Balance Sheet'!E38 -> 1736 | F64: ='Balance Sheet'!F38 -> 1485.4693 | G64: ='Balance Sheet'!G38 -> 1273.1813 | H64: ='Balance Sheet'!H38 -> 1035 | I64: ='Balance Sheet'!I38 -> 985 | J64: ='Balance Sheet'!J38 -> 935
B66: Other Long Term Liabilities | C66: ='Balance Sheet'!C40 -> 153 | D66: ='Balance Sheet'!D40 -> 157.3 | E66: ='Balance Sheet'!E40 -> 187.1 | F66: ='Balance Sheet'!F40 -> 187.1 | G66: ='Balance Sheet'!G40 -> 187.1 | H66: ='Balance Sheet'!H40 -> 187.1 | I66: ='Balance Sheet'!I40 -> 187.1 | J66: ='Balance Sheet'!J40 -> 187.1
B67: Post retirement Pension Cost | C67: ='Balance Sheet'!C41 -> 72.7 | D67: ='Balance Sheet'!D41 -> 54.4 | E67: ='Balance Sheet'!E41 -> 60.6 | F67: ='Balance Sheet'!F41 -> 60.6 | G67: ='Balance Sheet'!G41 -> 60.6 | H67: ='Balance Sheet'!H41 -> 60.6 | I67: ='Balance Sheet'!I41 -> 60.6 | J67: ='Balance Sheet'!J41 -> 60.6
B69: Common Stock & APIC | C69: ='Balance Sheet'!C43 -> 1000 | D69: ='Balance Sheet'!D43 -> 1000 | E69: ='Balance Sheet'!E43 -> 1000 | F69: ='Balance Sheet'!F43 -> 1000 | G69: ='Balance Sheet'!G43 -> 1000 | H69: ='Balance Sheet'!H43 -> 1000 | I69: ='Balance Sheet'!I43 -> 1000 | J69: ='Balance Sheet'!J43 -> 1000
B70: Treasury Stock | C70: ='Balance Sheet'!C44 -> -1500 | D70: ='Balance Sheet'!D44 -> -1575 | E70: ='Balance Sheet'!E44 -> -1655 | F70: ='Balance Sheet'!F44 -> -1755 | G70: ='Balance Sheet'!G44 -> -1855 | H70: ='Balance Sheet'!H44 -> -1955 | I70: ='Balance Sheet'!I44 -> -2055 | J70: ='Balance Sheet'!J44 -> -2155
B71: Retained Earnings | C71: ='Balance Sheet'!C45 -> 1000 | D71: ='Balance Sheet'!D45 -> 1564.1083 | E71: ='Balance Sheet'!E45 -> 2074.4133 | F71: ='Balance Sheet'!F45 -> 2561.0621 | G71: ='Balance Sheet'!G45 -> 3137.4668 | H71: ='Balance Sheet'!H45 -> 3819.2831 | I71: ='Balance Sheet'!I45 -> 4624.5639 | J71: ='Balance Sheet'!J45 -> 5573.2789
B72: Accumulated Other Comprehensive Income | C72: ='Balance Sheet'!C46 -> 0 | D72: ='Balance Sheet'!D46 -> 0 | E72: ='Balance Sheet'!E46 -> 0 | F72: ='Balance Sheet'!F46 -> 0 | G72: ='Balance Sheet'!G46 -> 0 | H72: ='Balance Sheet'!H46 -> 0 | I72: ='Balance Sheet'!I46 -> 0 | J72: ='Balance Sheet'!J46 -> 0
B73: Shareholder's Equity | C73: ='Balance Sheet'!C47 -> 500 | D73: ='Balance Sheet'!D47 -> 989.10834 | E73: ='Balance Sheet'!E47 -> 1419.4133 | F73: ='Balance Sheet'!F47 -> 1806.0621 | G73: ='Balance Sheet'!G47 -> 2282.4668 | H73: ='Balance Sheet'!H47 -> 2864.2831 | I73: ='Balance Sheet'!I47 -> 3569.5639 | J73: ='Balance Sheet'!J47 -> 4418.2789
B75: Total Liabilities & Equity | C75: ='Balance Sheet'!C49 -> 3631.1 | D75: ='Balance Sheet'!D49 -> 3786.3083 | E75: ='Balance Sheet'!E49 -> 3940.7133 | F75: ='Balance Sheet'!F49 -> 4135.4855 | G75: ='Balance Sheet'!G49 -> 4498.3414 | H75: ='Balance Sheet'!H49 -> 4957.3456 | I75: ='Balance Sheet'!I49 -> 5747.4599 | J75: ='Balance Sheet'!J49 -> 6703.7936
B79: Shares Oustanding (Million) | C79: ='Income Statement'!C24 -> 99.245 | D79: ='Income Statement'!D24 -> 97.995 | E79: ='Income Statement'!E24 -> 96.61569 | F79: ='Income Statement'!F24 -> 94.909212 | G79: ='Income Statement'!G24 -> 93.490005 | H79: ='Income Statement'!H24 -> 92.305415 | I79: ='Income Statement'!I24 -> 91.313227 | J79: ='Income Statement'!J24 -> 90.478741
B81: Per Share Data
B82: Diluted EPS | C82: ='Income Statement'!C26 -> 7.8047872 | D82: ='Income Statement'!D26 -> 7.6953757 | E82: ='Income Statement'!E26 -> 7.6623675 | F82: ='Income Statement'!F26 -> 7.325029 | G82: ='Income Statement'!G26 -> 8.8077357 | H82: ='Income Statement'!H26 -> 10.55218 | I82: ='Income Statement'!I26 -> 12.598408 | J82: ='Income Statement'!J26 -> 14.979288
B83: Cash per Share | C83: ='Balance Sheet'!C7/Dashboard!C79 -> 0.27709204 | D83: ='Balance Sheet'!D7/Dashboard!D79 -> 0.87359908 | E83: ='Balance Sheet'!E7/Dashboard!E79 -> 0.50419624 | F83: ='Balance Sheet'!F7/Dashboard!F79 -> 0.31609155 | G83: ='Balance Sheet'!G7/Dashboard!G79 -> -0.014129212 | H83: ='Balance Sheet'!H7/Dashboard!H79 -> 1.2949509 | I83: ='Balance Sheet'!I7/Dashboard!I79 -> 4.8608429 | J83: ='Balance Sheet'!J7/Dashboard!J79 -> 9.6102752
B84: Book Value (BV) | C84: ='Balance Sheet'!C47/Dashboard!C79 -> 5.0380372 | D84: ='Balance Sheet'!D47/Dashboard!D79 -> 10.093457 | E84: ='Balance Sheet'!E47/Dashboard!E79 -> 14.691333 | F84: ='Balance Sheet'!F47/Dashboard!F79 -> 19.029366 | G84: ='Balance Sheet'!G47/Dashboard!G79 -> 24.414019 | H84: ='Balance Sheet'!H47/Dashboard!H79 -> 31.030499 | I84: ='Balance Sheet'!I47/Dashboard!I79 -> 39.091423 | J84: ='Balance Sheet'!J47/Dashboard!J79 -> 48.832233
B85: Dividends per Share (DPS) | C85: ='Shareholder''s Equity Forecast'!C7/Dashboard!C79 -> 1.5114112 | D85: ='Shareholder''s Equity Forecast'!D7/Dashboard!D79 -> 1.9388744 | E85: ='Shareholder''s Equity Forecast'!E7/Dashboard!E79 -> 2.3805657 | F85: ='Shareholder''s Equity Forecast'!F7/Dashboard!F79 -> 2.1975085 | G85: ='Shareholder''s Equity Forecast'!G7/Dashboard!G79 -> 2.6423205 | H85: ='Shareholder''s Equity Forecast'!H7/Dashboard!H79 -> 3.1656539 | I85: ='Shareholder''s Equity Forecast'!I7/Dashboard!I79 -> 3.7795222 | J85: ='Shareholder''s Equity Forecast'!J7/Dashboard!J79 -> 4.4937864
B87: Effective Tax Rates (%) | C87: ='Income Statement'!C23 -> 0.18429082 | D87: ='Income Statement'!D23 -> 0.22185342 | E87: ='Income Statement'!E23 -> 0.25620289 | F87: ='Income Statement'!F23 -> 0.25 | G87: ='Income Statement'!G23 -> 0.25 | H87: ='Income Statement'!H23 -> 0.25 | I87: ='Income Statement'!I23 -> 0.25 | J87: ='Income Statement'!J23 -> 0.25
B90: Valuation Ratios (x)
B91: EV / Revenue | C91: ='DCF Valuations'!C33/'Income Statement'!E5 -> 4.8382175
B92: EV / EBITDA | C92: ='DCF Valuations'!C33/'Income Statement'!E10 -> 15.946439
B93: PE Ratio | C93: ='DCF Valuations'!C41/'Income Statement'!E26 -> 23.945569
B95: Revenue Split by Segment | C95: Notebook | D95: Writing Pads | E95: Premium Journal
C96: ='Revenue and Cost Forecast'!E13/'Revenue and Cost Forecast'!E34 -> 0.60196238 | D96: ='Revenue and Cost Forecast'!E22/'Revenue and Cost Forecast'!E34 -> 0.13704864 | E96: ='Revenue and Cost Forecast'!E32/'Revenue and Cost Forecast'!E34 -> 0.26098897
B97: DCF Valuation
B98: WACC | C98: ='DCF Valuations'!C18 -> 0.057541669
B99: Growth Rates | C99: ='DCF Valuations'!C19 -> 0.01
B100: Cost of Equity | C100: ='Cost of Capital Calculation'!G33 -> 0.097986277
B101: Fair Valuation | C101: ='DCF Valuations'!C41 -> 183.47975
B103: Target Price - | C103: ='DCF Valuations'!D41 -> 194.6555
B104: BUY/ Hold / SELL? | C104: =IF(C103>C101*1.05,"BUY",IF(C103<C101*0.95,"SELL","HOLD")) -> BUY

Sheet Income Statement
A1: Big Books Company
B2: Income Statement
C3: Actuals | F3: Forecast
B4: ($ in Million Except Per Share Amounts) | C4: Historical 1 | D4: Historical 2 | E4: Historical 3 | F4: Forecast 1 | G4: Forecast 2 | H4: Forecast 3 | I4: Forecast 4 | J4: Forecast 5
B5: Net Sales | C5: 2904.94 | D5: 3408 | E5: 3958.96 | F5: ='Revenue and Cost Forecast'!F34 -> 4119.966 | G5: ='Revenue and Cost Forecast'!G34 -> 4803.7718 | H5: ='Revenue and Cost Forecast'!H34 -> 5602.8773 | I5: ='Revenue and Cost Forecast'!I34 -> 6536.9387 | J5: ='Revenue and Cost Forecast'!J34 -> 7628.9884
B6: Cost of Sales | C6: 1494.8366 | D6: 1866.1246 | E6: 2309.7272 | F6: ='Revenue and Cost Forecast'!F50 -> 2502.2446 | G6: ='Revenue and Cost Forecast'!G50 -> 2916.6145 | H6: ='Revenue and Cost Forecast'!H50 -> 3400.774 | I6: ='Revenue and Cost Forecast'!I50 -> 3966.6171 | J6: ='Revenue and Cost Forecast'!J50 -> 4628.0813
B7: Gross Profit | C7: =C5-C6 -> 1410.1034 | D7: =D5-D6 -> 1541.8754 | E7: =E5-E6 -> 1649.2328 | F7: =F5-F6 -> 1617.7214 | G7: =G5-G6 -> 1887.1573 | H7: =H5-H6 -> 2202.1033 | I7: =I5-I6 -> 2570.3216 | J7: =J5-J6 -> 3000.9071
B9: Selling, General & Admin Costs | C9: 305.14255 | D9: 388.2872 | E9: 448.0675 | F9: ='Revenue and Cost Forecast'!F65 -> 463.83868 | G9: ='Revenue and Cost Forecast'!G65 -> 540.94103 | H9: ='Revenue and Cost Forecast'!H65 -> 631.05976 | I9: ='Revenue and Cost Forecast'!I65 -> 736.41607 | J9: ='Revenue and Cost Forecast'!J65 -> 859.61298
B10: EBITDA | C10: =C7-C9 -> 1104.9608 | D10: =D7-D9 -> 1153.5882 | E10: =E7-E9 -> 1201.1653 | F10: =F7-F9 -> 1153.8827 | G10: =G7-G9 -> 1346.2162 | H10: =H7-H9 -> 1571.0435 | I10: =I7-I9 -> 1833.9055 | J10: =J7-J9 -> 2141.2941
B12: Depreciation | C12: 101.9 | D12: 123.1 | E12: 140 | F12: ='Depreciation Capex Forecast'!F57 -> 151.53313 | G12: ='Depreciation Capex Forecast'!G57 -> 179.55514 | H12: ='Depreciation Capex Forecast'!H57 -> 212.23859 | I12: ='Depreciation Capex Forecast'!I57 -> 250.37073 | J12: ='Depreciation Capex Forecast'!J57 -> 294.87316
B13: Amortization | C13: 9.367 | D13: 10.666 | E13: 13.035 | F13: ='Amortization Forecast'!F28 -> 13.295973 | G13: ='Amortization Forecast'!G28 -> 17.13899 | H13: ='Amortization Forecast'!H28 -> 21.621292 | I13: ='Amortization Forecast'!I28 -> 26.850843 | J13: ='Amortization Forecast'!J28 -> 32.954034
B14: EBIT | C14: =C10-C12-C13 -> 993.69382 | D14: =D10-D12-D13 -> 1019.8222 | E14: =E10-E12-E13 -> 1048.1303 | F14: =F10-F12-F13 -> 989.05358 | G14: =G10-G12-G13 -> 1149.5221 | H14: =H10-H12-H13 -> 1337.1836 | I14: =I10-I12-I13 -> 1556.684 | J14: =J10-J12-J13 -> 1813.4669
B16: Interest Expense | C16: 44.10772 | D16: 60.11464 | E16: 63.765 | F16: ='Debt Forecast'!F48 -> 73.105859 | G16: ='Debt Forecast'!G48 -> 62.785391 | H16: ='Debt Forecast'!H48 -> 52.279533 | I16: ='Debt Forecast'!I48 -> 45.45 | J16: ='Debt Forecast'!J48 -> 43.2
B17: Interest Income | C17: 0 | D17: 9.4007832 | E17: 10.939602 | F17: ='Debt Forecast'!F57 -> 11.002482 | G17: ='Debt Forecast'!G57 -> 11.176884 | H17: ='Debt Forecast'!H57 -> 13.793676 | I17: ='Debt Forecast'!I57 -> 22.634329 | J17: ='Debt Forecast'!J57 -> 36.809235
B18: Pretax Income | C18: =C14-C16+C17 -> 949.5861 | D18: =D14-D16+D17 -> 969.10834 | E18: =E14-E16+E17 -> 995.30492 | F18: =F14-F16+F17 -> 926.9502 | G18: =G14-G16+G17 -> 1097.9136 | H18: =H14-H16+H17 -> 1298.6978 | I18: =I14-I16+I17 -> 1533.8683 | J18: =J14-J16+J17 -> 1807.0762
B20: Income Taxes | C20: 175 | D20: 215 | E20: 255 | F20: =F18*F23 -> 231.73755 | G20: =G18*G23 -> 274.4784 | H20: =H18*H23 -> 324.67445 | I20: =I18*I23 -> 383.46707 | J20: =J18*J23 -> 451.76904
B21: Net Income | C21: =C18-C20 -> 774.5861 | D21: =D18-D20 -> 754.10834 | E21: =E18-E20 -> 740.30492 | F21: =F18-F20 -> 695.21265 | G21: =G18-G20 -> 823.4352 | H21: =H18-H20 -> 974.02334 | I21: =I18-I20 -> 1150.4012 | J21: =J18-J20 -> 1355.3071
B23: Effective Tax Rate | C23: =C20/C18 -> 0.18429082 | D23: =D20/D18 -> 0.22185342 | E23: =E20/E18 -> 0.25620289 | F23: 0.25 | G23: 0.25 | H23: 0.25 | I23: 0.25 | J23: 0.25
B24: Outstanding Shares | C24: 99.245 | D24: 97.995 | E24: 96.61569 | F24: ='Shareholder''s Equity Forecast'!F25 -> 94.909212 | G24: ='Shareholder''s Equity Forecast'!G25 -> 93.490005 | H24: ='Shareholder''s Equity Forecast'!H25 -> 92.305415 | I24: ='Shareholder''s Equity Forecast'!I25 -> 91.313227 | J24: ='Shareholder''s Equity Forecast'!J25 -> 90.478741
B26: Earnings Per Share | C26: =C21/C24 -> 7.8047872 | D26: =D21/D24 -> 7.6953757 | E26: =E21/E24 -> 7.6623675 | F26: =F21/F24 -> 7.325029 | G26: =G21/G24 -> 8.8077357 | H26: =H21/H24 -> 10.55218 | I26: =I21/I24 -> 12.598408 | J26: =J21/J24 -> 14.979288
B28: Dividends | C28: 150 | D28: 190 | E28: 230 | F28: ='Shareholder''s Equity Forecast'!F7 -> 208.56379 | G28: ='Shareholder''s Equity Forecast'!G7 -> 247.03056 | H28: ='Shareholder''s Equity Forecast'!H7 -> 292.207 | I28: ='Shareholder''s Equity Forecast'!I7 -> 345.12036 | J28: ='Shareholder''s Equity Forecast'!J7 -> 406.59214
B29: Dividend Per Share | C29: =C28/C24 -> 1.5114112 | D29: =D28/D24 -> 1.9388744 | E29: =E28/E24 -> 2.3805657 | F29: =F28/F24 -> 2.1975085 | G29: =G28/G24 -> 2.6423205 | H29: =H28/H24 -> 3.1656539 | I29: =I28/I24 -> 3.7795222 | J29: =J28/J24 -> 4.4937864

Sheet Balance Sheet
A1: Big Books Company
B2: Balance Sheet
C3: Actuals | F3: Forecast
B4: ($ in Million Except Per Share Amounts) | C4: Historical 1 | D4: Historical 2 | E4: Historical 3 | F4: Forecast 1 | G4: Forecast 2 | H4: Forecast 3 | I4: Forecast 4 | J4: Forecast 5
B6: Current Assets
B7: Cash & Cash Equivalents | C7: 27.5 | D7: 85.608342 | E7: 48.713267 | F7: ='Cash Flow Statement'!F36 -> 30 | G7: ='Cash Flow Statement'!G36 -> -1.3209401 | H7: ='Cash Flow Statement'!H36 -> 119.53098 | I7: ='Cash Flow Statement'!I36 -> 443.85925 | J7: ='Cash Flow Statement'!J36 -> 869.5256
B8: Marketable Securities | C8: 40 | D8: 50 | E8: 60 | F8: ='Other Assets & Liabilities'!F7 -> 70 | G8: ='Other Assets & Liabilities'!G7 -> 80 | H8: ='Other Assets & Liabilities'!H7 -> 90 | I8: ='Other Assets & Liabilities'!I7 -> 100 | J8: ='Other Assets & Liabilities'!J7 -> 110
B9: Receivables | C9: 462.9 | D9: 473.7 | E9: 473 | F9: ='Working Capital Forecast'!F7 -> 474.07828 | G9: ='Working Capital Forecast'!G7 -> 552.76278 | H9: ='Working Capital Forecast'!H7 -> 644.71465 | I9: ='Working Capital Forecast'!I7 -> 752.19568 | J9: ='Working Capital Forecast'!J7 -> 877.8562
B10: Inventory | C10: 327 | D10: 350.2 | E10: 383.8 | F10: ='Working Capital Forecast'!F8 -> 411.32788 | G10: ='Working Capital Forecast'!G8 -> 479.44348 | H10: ='Working Capital Forecast'!H8 -> 559.03134 | I10: ='Working Capital Forecast'!I8 -> 652.04664 | J10: ='Working Capital Forecast'!J8 -> 760.78048
B11: Other Current Assets | C11: 87.4 | D11: 82.8 | E11: 83.5 | F11: ='Working Capital Forecast'!F9 -> 82.39932 | G11: ='Working Capital Forecast'!G9 -> 96.075436 | H11: ='Working Capital Forecast'!H9 -> 112.05755 | I11: ='Working Capital Forecast'!I9 -> 130.73877 | J11: ='Working Capital Forecast'!J9 -> 152.57977
B12: Total Current Assets | C12: =SUM(C7:C11) -> 944.8 | D12: =SUM(D7:D11) -> 1042.3083 | E12: =SUM(E7:E11) -> 1049.0133 | F12: =SUM(F7:F11) -> 1067.8055 | G12: =SUM(G7:G11) -> 1206.9608 | H12: =SUM(H7:H11) -> 1525.3345 | I12: =SUM(I7:I11) -> 2078.8403 | J12: =SUM(J7:J11) -> 2770.742
B14: Long Term Securities | C14: 160 | D14: 180 | E14: 200 | F14: ='Other Assets & Liabilities'!F8 -> 220 | G14: ='Other Assets & Liabilities'!G8 -> 240 | H14: ='Other Assets & Liabilities'!H8 -> 260 | I14: ='Other Assets & Liabilities'!I8 -> 280 | J14: ='Other Assets & Liabilities'!J8 -> 300
B16: Land | C16: 30 | D16: 30 | E16: 30 | F16: ='Depreciation Capex Forecast'!F7 -> 30 | G16: ='Depreciation Capex Forecast'!G7 -> 30 | H16: ='Depreciation Capex Forecast'!H7 -> 30 | I16: ='Depreciation Capex Forecast'!I7 -> 30 | J16: ='Depreciation Capex Forecast'!J7 -> 30
B17: Machinery and equipment | C17: =550+80 -> 630 | D17: 700 | E17: 875 | F17: ='Depreciation Capex Forecast'!F8 -> 1080.9983 | G17: ='Depreciation Capex Forecast'!G8 -> 1321.1869 | H17: ='Depreciation Capex Forecast'!H8 -> 1601.3308 | I17: ='Depreciation Capex Forecast'!I8 -> 1928.1777 | J17: ='Depreciation Capex Forecast'!J8 -> 2309.6271
B18: Automobiles and trucks | C18: 250 | D18: 325 | E18: 400 | F18: ='Depreciation Capex Forecast'!F9 -> 482.39932 | G18: ='Depreciation Capex Forecast'!G9 -> 578.47476 | H18: ='Depreciation Capex Forecast'!H9 -> 690.5323 | I18: ='Depreciation Capex Forecast'!I9 -> 821.27107 | J18: ='Depreciation Capex Forecast'!J9 -> 973.85084
B19: Gross PPE | C19: =SUM(C16:C18) -> 910 | D19: =SUM(D16:D18) -> 1055 | E19: =SUM(E16:E18) -> 1305 | F19: =SUM(F16:F18) -> 1593.3976 | G19: =SUM(G16:G18) -> 1929.6616 | H19: =SUM(H16:H18) -> 2321.8631 | I19: =SUM(I16:I18) -> 2779.4488 | J19: =SUM(J16:J18) -> 3313.4779
B20: Accumulated Depreciation | C20: -101.9 | D20: -225 | E20: -365 | F20: =E20-'Depreciation Capex Forecast'!F57 -> -516.53313 | G20: =F20-'Depreciation Capex Forecast'!G57 -> -696.08827 | H20: =G20-'Depreciation Capex Forecast'!H57 -> -908.32686 | I20: =H20-'Depreciation Capex Forecast'!I57 -> -1158.6976 | J20: =I20-'Depreciation Capex Forecast'!J57 -> -1453.5708
B21: Net PPE | C21: =C19+C20 -> 808.1 | D21: =D19+D20 -> 830 | E21: =E19+E20 -> 940 | F21: =F19+F20 -> 1076.8645 | G21: =G19+G20 -> 1233.5734 | H21: =H19+H20 -> 1413.5362 | I21: =I19+I20 -> 1620.7512 | J21: =J19+J20 -> 1859.9072
B23: Other Assets
B24: Intangibles, net | C24: 46.5 | D24: 62.3 | E24: 80 | F24: ='Amortization Forecast'!F13 -> 99.663755 | G24: ='Amortization Forecast'!G13 -> 120.95494 | H24: ='Amortization Forecast'!H13 -> 144.15667 | I24: ='Amortization Forecast'!I13 -> 169.60133 | J24: ='Amortization Forecast'!J13 -> 197.67921
B25: Goodwill | C25: 1671.7 | D25: 1671.7 | E25: 1671.7 | F25: ='Other Assets & Liabilities'!C6 -> 1671.7 | G25: ='Other Assets & Liabilities'!D6 -> 1671.7 | H25: ='Other Assets & Liabilities'!E6 -> 1671.7 | I25: ='Other Assets & Liabilities'!F6 -> 1671.7 | J25: ='Other Assets & Liabilities'!G6 -> 1671.7
B27: Total Assets | C27: =C12+C21+C24+C25+C14 -> 3631.1 | D27: =D12+D21+D24+D25+D14 -> 3786.3083 | E27: =E12+E21+E24+E25+E14 -> 3940.7133 | F27: =F12+F21+F24+F25+F14 -> 4136.0337 | G27: =G12+G21+G24+G25+G14 -> 4473.1891 | H27: =H12+H21+H24+H25+H14 -> 5014.7274 | I27: =I12+I21+I24+I25+I14 -> 5820.8928 | J27: =J12+J21+J24+J25+J14 -> 6800.0284
B29: Current Liabilities
B30: Accounts Payable | C30: 206.4 | D30: 221.4 | E30: 279.1 | F30: ='Working Capital Forecast'!F12 -> 308.49591 | G30: ='Working Capital Forecast'!G12 -> 359.58261 | H30: ='Working Capital Forecast'!H12 -> 419.27351 | I30: ='Working Capital Forecast'!I12 -> 489.03498 | J30: ='Working Capital Forecast'!J12 -> 570.58536
B31: Accrued Liabilities | C31: 180.7 | D31: 161.3 | E31: 176.7 | F31: ='Working Capital Forecast'!F13 -> 200.17957 | G31: ='Working Capital Forecast'!G13 -> 233.32916 | H31: ='Working Capital Forecast'!H13 -> 272.06192 | I31: ='Working Capital Forecast'!I13 -> 317.32937 | J31: ='Working Capital Forecast'!J13 -> 370.2465
B32: Other Current Liabilities | C32: 68.3 | D32: 62.8 | E32: 81.8 | F32: ='Working Capital Forecast'!F14 -> 87.578562 | G32: ='Working Capital Forecast'!G14 -> 102.08151 | H32: ='Working Capital Forecast'!H14 -> 119.02709 | I32: ='Working Capital Forecast'!I14 -> 138.8316 | J32: ='Working Capital Forecast'!J14 -> 161.98284
B33: Total Current Liabilities | C33: =SUM(C30:C32) -> 455.4 | D33: =SUM(D30:D32) -> 445.5 | E33: =SUM(E30:E32) -> 537.6 | F33: =SUM(F30:F32) -> 596.25405 | G33: =SUM(G30:G32) -> 694.99328 | H33: =SUM(H30:H32) -> 810.36252 | I33: =SUM(I30:I32) -> 945.19594 | J33: =SUM(J30:J32) -> 1102.8147
B35: Loan Funds
B36: Revolving Credit Facility | C36: 250 | D36: 150 | E36: 101 | F36: ='Debt Forecast'!F28 -> 150.4693 | G36: ='Debt Forecast'!G28 -> 138.18131 | H36: ='Debt Forecast'!H28 -> 0 | I36: ='Debt Forecast'!I28 -> 0 | J36: ='Debt Forecast'!J28 -> 0
B37: Long Term Debt | C37: 2200 | D37: 1990 | E37: =1535+100 -> 1635 | F37: ='Debt Forecast'!F34 -> 1335 | G37: ='Debt Forecast'!G34 -> 1135 | H37: ='Debt Forecast'!H34 -> 1035 | I37: ='Debt Forecast'!I34 -> 985 | J37: ='Debt Forecast'!J34 -> 935
B38: Total Loan Funds | C38: =SUM(C36:C37) -> 2450 | D38: =SUM(D36:D37) -> 2140 | E38: =SUM(E36:E37) -> 1736 | F38: =SUM(F36:F37) -> 1485.4693 | G38: =SUM(G36:G37) -> 1273.1813 | H38: =SUM(H36:H37) -> 1035 | I38: =SUM(I36:I37) -> 985 | J38: =SUM(J36:J37) -> 935
B40: Other Long Term Liabilities | C40: 153 | D40: 157.3 | E40: 187.1 | F40: ='Other Assets & Liabilities'!F9 -> 187.1 | G40: ='Other Assets & Liabilities'!G9 -> 187.1 | H40: ='Other Assets & Liabilities'!H9 -> 187.1 | I40: ='Other Assets & Liabilities'!I9 -> 187.1 | J40: ='Other Assets & Liabilities'!J9 -> 187.1
B41: Post retirement Pension Cost | C41: 72.7 | D41: 54.4 | E41: 60.6 | F41: ='Other Assets & Liabilities'!F10 -> 60.6 | G41: ='Other Assets & Liabilities'!G10 -> 60.6 | H41: ='Other Assets & Liabilities'!H10 -> 60.6 | I41: ='Other Assets & Liabilities'!I10 -> 60.6 | J41: ='Other Assets & Liabilities'!J10 -> 60.6
B43: Common Stock & APIC | C43: 1000 | D43: 1000 | E43: 1000 | F43: ='Shareholder''s Equity Forecast'!F12 -> 1000 | G43: ='Shareholder''s Equity Forecast'!G12 -> 1000 | H43: ='Shareholder''s Equity Forecast'!H12 -> 1000 | I43: ='Shareholder''s Equity Forecast'!I12 -> 1000 | J43: ='Shareholder''s Equity Forecast'!J12 -> 1000
B44: Treasury Stock | C44: -1500 | D44: -1575 | E44: -1655 | F44: ='Shareholder''s Equity Forecast'!F13 -> -1755 | G44: ='Shareholder''s Equity Forecast'!G13 -> -1855 | H44: ='Shareholder''s Equity Forecast'!H13 -> -1955 | I44: ='Shareholder''s Equity Forecast'!I13 -> -2055 | J44: ='Shareholder''s Equity Forecast'!J13 -> -2155
B45: Retained Earnings | C45: 1000 | D45: 1564.1083 | E45: 2074.4133 | F45: ='Shareholder''s Equity Forecast'!F14 -> 2561.0621 | G45: ='Shareholder''s Equity Forecast'!G14 -> 3137.4668 | H45: ='Shareholder''s Equity Forecast'!H14 -> 3819.2831 | I45: ='Shareholder''s Equity Forecast'!I14 -> 4624.5639 | J45: ='Shareholder''s Equity Forecast'!J14 -> 5573.2789
B46: Accumulated Other Comprehensive Income | C46: 0 | D46: 0 | E46: 0 | F46: ='Shareholder''s Equity Forecast'!F15 -> 0 | G46: ='Shareholder''s Equity Forecast'!G15 -> 0 | H46: ='Shareholder''s Equity Forecast'!H15 -> 0 | I46: ='Shareholder''s Equity Forecast'!I15 -> 0 | J46: ='Shareholder''s Equity Forecast'!J15 -> 0
B47: Shareholder's Equity | C47: =SUM(C43:C46) -> 500 | D47: =SUM(D43:D46) -> 989.10834 | E47: =SUM(E43:E46) -> 1419.4133 | F47: =SUM(F43:F46) -> 1806.0621 | G47: =SUM(G43:G46) -> 2282.4668 | H47: =SUM(H43:H46) -> 2864.2831 | I47: =SUM(I43:I46) -> 3569.5639 | J47: =SUM(J43:J46) -> 4418.2789
B49: Total Liabilities & Equity | C49: =C47+C41+C40+C38+C33 -> 3631.1 | D49: =D47+D41+D40+D38+D33 -> 3786.3083 | E49: =E47+E41+E40+E38+E33 -> 3940.7133 | F49: =F47+F41+F40+F38+F33 -> 4135.4855 | G49: =G47+G41+G40+G38+G33 -> 4498.3414 | H49: =H47+H41+H40+H38+H33 -> 4957.3456 | I49: =I47+I41+I40+I38+I33 -> 5747.4599 | J49: =J47+J41+J40+J38+J33 -> 6703.7936
B52: Check | C52: =C49-C27 -> 0 | D52: =D49-D27 -> 0 | E52: =E49-E27 -> 0

Sheet Cash Flow Statement
A1: Big Books Company
B2: Cash Flow Statement
C3: Actuals | F3: Forecast
B4: ($ in Million Except Per Share Amounts) | C4: Historical 1 | D4: Historical 2 | E4: Historical 3 | F4: Forecast 1 | G4: Forecast 2 | H4: Forecast 3 | I4: Forecast 4 | J4: Forecast 5
B5: Operating Activities
B6: Net Income | D6: 754.10834 | E6: 740.30492 | F6: ='Income Statement'!F21 -> 695.99587 | G6: ='Income Statement'!G21 -> 829.82064 | H6: ='Income Statement'!H21 -> 988.81888 | I6: ='Income Statement'!I21 -> 1173.3315 | J6: ='Income Statement'!J21 -> 1387.8812
B7: Add Depreciation | D7: 123.1 | E7: 140 | F7: ='Income Statement'!F12 -> 151.53313 | G7: ='Income Statement'!G12 -> 179.55514 | H7: ='Income Statement'!H12 -> 212.23859 | I7: ='Income Statement'!I12 -> 250.37073 | J7: ='Income Statement'!J12 -> 294.87316
B8: Add Amortization | D8: 10.666 | E8: 13.035 | F8: ='Income Statement'!F13 -> 13.295973 | G8: ='Income Statement'!G13 -> 17.13899 | H8: ='Income Statement'!H13 -> 21.621292 | I8: ='Income Statement'!I13 -> 26.850843 | J8: ='Income Statement'!J13 -> 32.954034
B9: Change in Working Capital
B10: Change in Receivable | D10: -10.8 | E10: 0.7 | F10: ='Working Capital Forecast'!F35 -> -1.078279 | G10: ='Working Capital Forecast'!G35 -> -78.684503 | H10: ='Working Capital Forecast'!H35 -> -91.951864 | I10: ='Working Capital Forecast'!I35 -> -107.48104 | J10: ='Working Capital Forecast'!J35 -> -125.66052
B11: change in Inventory | D11: -23.2 | E11: -33.6 | F11: ='Working Capital Forecast'!F36 -> -27.527884 | G11: ='Working Capital Forecast'!G36 -> -68.1156 | H11: ='Working Capital Forecast'!H36 -> -79.587859 | I11: ='Working Capital Forecast'!I36 -> -93.015299 | J11: ='Working Capital Forecast'!J36 -> -108.73384
B12: Change in Other Current Assets | D12: 4.6 | E12: -0.7 | F12: ='Working Capital Forecast'!F37 -> 1.1006801 | G12: ='Working Capital Forecast'!G37 -> -13.676116 | H12: ='Working Capital Forecast'!H37 -> -15.98211 | I12: ='Working Capital Forecast'!I37 -> -18.681228 | J12: ='Working Capital Forecast'!J37 -> -21.840994
B13: Change in Accounts Payable | D13: 15 | E13: 57.7 | F13: ='Working Capital Forecast'!F38 -> 29.395913 | G13: ='Working Capital Forecast'!G38 -> 51.0867 | H13: ='Working Capital Forecast'!H38 -> 59.690894 | I13: ='Working Capital Forecast'!I38 -> 69.761474 | J13: ='Working Capital Forecast'!J38 -> 81.550381
B14: Change in Accrued Liabilities | D14: -19.4 | E14: 15.4 | F14: ='Working Capital Forecast'!F39 -> 23.47957 | G14: ='Working Capital Forecast'!G39 -> 33.149592 | H14: ='Working Capital Forecast'!H39 -> 38.732758 | I14: ='Working Capital Forecast'!I39 -> 45.267445 | J14: ='Working Capital Forecast'!J39 -> 52.917136
B15: Change in Other Current Liabilities | D15: -5.5 | E15: 19 | F15: ='Working Capital Forecast'!F40 -> 5.778562 | G15: ='Working Capital Forecast'!G40 -> 14.502947 | H15: ='Working Capital Forecast'!H40 -> 16.945582 | I15: ='Working Capital Forecast'!I40 -> 19.804507 | J15: ='Working Capital Forecast'!J40 -> 23.151247
B16: Change in Assets & Liabilities (if any) | D16: -14 | E16: 36 | F16: =('Balance Sheet'!F40-'Balance Sheet'!E40)+('Balance Sheet'!F41-'Balance Sheet'!E41) -> 0 | G16: =('Balance Sheet'!G40-'Balance Sheet'!F40)+('Balance Sheet'!G41-'Balance Sheet'!F41) -> 0 | H16: =('Balance Sheet'!H40-'Balance Sheet'!G40)+('Balance Sheet'!H41-'Balance Sheet'!G41) -> 0 | I16: =('Balance Sheet'!I40-'Balance Sheet'!H40)+('Balance Sheet'!I41-'Balance Sheet'!H41) -> 0 | J16: =('Balance Sheet'!J40-'Balance Sheet'!I40)+('Balance Sheet'!J41-'Balance Sheet'!I41) -> 0
B17: Cash Flow from Operating Activities | D17: =SUM(D6:D16) -> 834.57434 | E17: =SUM(E6:E16) -> 987.83992 | F17: =SUM(F6:F16) -> 891.97354 | G17: =SUM(G6:G16) -> 964.77779 | H17: =SUM(H6:H16) -> 1150.5262 | I17: =SUM(I6:I16) -> 1366.2089 | J17: =SUM(J6:J16) -> 1617.0918
B19: Investment Activities
B20: Purchase of Marketable Securities | D20: -10 | E20: -10 | F20: =-('Balance Sheet'!F8-'Balance Sheet'!E8) -> -10 | G20: =-('Balance Sheet'!G8-'Balance Sheet'!F8) -> -10 | H20: =-('Balance Sheet'!H8-'Balance Sheet'!G8) -> -10 | I20: =-('Balance Sheet'!I8-'Balance Sheet'!H8) -> -10 | J20: =-('Balance Sheet'!J8-'Balance Sheet'!I8) -> -10
B21: Purchase of Long Term Securities | D21: -20 | E21: -20 | F21: =-('Balance Sheet'!F14-'Balance Sheet'!E14) -> -20 | G21: =-('Balance Sheet'!G14-'Balance Sheet'!F14) -> -20 | H21: =-('Balance Sheet'!H14-'Balance Sheet'!G14) -> -20 | I21: =-('Balance Sheet'!I14-'Balance Sheet'!H14) -> -20 | J21: =-('Balance Sheet'!J14-'Balance Sheet'!I14) -> -20
B22: Capital Expenditures | D22: -145 | E22: -250 | F22: =-'Depreciation Capex Forecast'!F18 -> -288.39762 | G22: =-'Depreciation Capex Forecast'!G18 -> -336.26403 | H22: =-'Depreciation Capex Forecast'!H18 -> -392.20141 | I22: =-'Depreciation Capex Forecast'!I18 -> -457.58571 | J22: =-'Depreciation Capex Forecast'!J18 -> -534.02919
B23: Additions to Intangibles | D23: -26.466 | E23: -30.735 | F23: =-'Amortization Forecast'!F7 -> -32.959728 | G23: =-'Amortization Forecast'!G7 -> -38.430174 | H23: =-'Amortization Forecast'!H7 -> -44.823018 | I23: =-'Amortization Forecast'!I7 -> -52.295509 | J23: =-'Amortization Forecast'!J7 -> -61.031907
B24: Cash Flow from Investing Activities | D24: =SUM(D20:D23) -> -201.466 | E24: =SUM(E20:E23) -> -310.735 | F24: =SUM(F20:F23) -> -351.35735 | G24: =SUM(G20:G23) -> -404.6942 | H24: =SUM(H20:H23) -> -467.02443 | I24: =SUM(I20:I23) -> -539.88122 | J24: =SUM(J20:J23) -> -625.06109
B26: Financing Activities
B27: Proceeds from/ (repayment of) Revolving Credit Facility | D27: -100 | E27: -49 | F27: ='Debt Forecast'!F27 -> 49.4693 | G27: ='Debt Forecast'!G27 -> -42.458335 | H27: ='Debt Forecast'!H27 -> -66.004154 | I27: ='Debt Forecast'!I27 -> 0 | J27: ='Debt Forecast'!J27 -> 0
B28: Issuance of Long Term Debt | D28: 0 | E28: 0 | F28: 0 | G28: 0 | H28: 0 | I28: 0 | J28: 0
B29: (Repayment) of Long Term Debt | D29: -210 | E29: -355 | F29: ='Debt Forecast'!F33 -> -300 | G29: ='Debt Forecast'!G33 -> -200 | H29: ='Debt Forecast'!H33 -> -100 | I29: ='Debt Forecast'!I33 -> -50 | J29: ='Debt Forecast'!J33 -> -50
B30: Issuance/ (Repurchase of) Equity | D30: -75 | E30: -80 | F30: ='Shareholder''s Equity Forecast'!F19 -> -100 | G30: ='Shareholder''s Equity Forecast'!G19 -> -100 | H30: ='Shareholder''s Equity Forecast'!H19 -> -100 | I30: ='Shareholder''s Equity Forecast'!I19 -> -100 | J30: ='Shareholder''s Equity Forecast'!J19 -> -100
B31: Dividends | D31: -190 | E31: -230 | F31: =-'Shareholder''s Equity Forecast'!F7 -> -208.79876 | G31: =-'Shareholder''s Equity Forecast'!G7 -> -248.94619 | H31: =-'Shareholder''s Equity Forecast'!H7 -> -296.64566 | I31: =-'Shareholder''s Equity Forecast'!I7 -> -351.99945 | J31: =-'Shareholder''s Equity Forecast'!J7 -> -416.36436
B32: Cash Flow from Financing Activities | D32: =SUM(D27:D31) -> -575 | E32: =SUM(E27:E31) -> -714 | F32: =SUM(F27:F31) -> -559.32946 | G32: =SUM(G27:G31) -> -591.40453 | H32: =SUM(H27:H31) -> -562.64982 | I32: =SUM(I27:I31) -> -501.99945 | J32: =SUM(J27:J31) -> -566.36436
B34: Net Change in Cash | D34: =D32+D24+D17 -> 58.108342 | E34: =E32+E24+E17 -> -36.895075 | F34: =F32+F24+F17 -> -18.713267 | G34: =G32+G24+G17 -> -31.32094 | H34: =H32+H24+H17 -> 120.85192 | I34: =I32+I24+I17 -> 324.32827 | J34: =J32+J24+J17 -> 425.66635
B35: Beginning Cash Balance | D35: =C36 -> 27.5 | E35: =D36 -> 85.608342 | F35: =E36 -> 48.713267 | G35: =F36 -> 30 | H35: =G36 -> -1.3209401 | I35: =H36 -> 119.53098 | J35: =I36 -> 443.85925
B36: Ending Cash Balance | C36: ='Balance Sheet'!C7 -> 27.5 | D36: =SUM(D34:D35) -> 85.608342 | E36: =SUM(E34:E35) -> 48.713267 | F36: =SUM(F34:F35) -> 30 | G36: =SUM(G34:G35) -> -1.3209401 | H36: =SUM(H34:H35) -> 119.53098 | I36: =SUM(I34:I35) -> 443.85925 | J36: =SUM(J34:J35) -> 869.5256
B38: Check

Sheet Revenue and Cost Forecast
A1: Big Books Company
B2: Revenue and Cost Forecast
C3: Actuals | F3: Forecast
B4: ($ in Million Except Per Share Amounts) | C4: Historical 1 | D4: Historical 2 | E4: Historical 3 | F4: Forecast 1 | G4: Forecast 2 | H4: Forecast 3 | I4: Forecast 4 | J4: Forecast 5
B6: Segment 1 - Notebook
B7: Notebook (Million Units) | C7: 340 | D7: 391 | E7: =D7*(1+15%) -> 449.65 | F7: =E7*(1+F8) -> 472.1325 | G7: =F7*(1+G8) -> 542.95237 | H7: =G7*(1+H8) -> 624.39523 | I7: =H7*(1+I8) -> 718.05452 | J7: =I7*(1+J8) -> 825.76269
B8: % Growth | D8: =D7/C7-1 -> 0.15 | E8: =E7/D7-1 -> 0.15 | F8: 0.05 | G8: 0.15 | H8: 0.15 | I8: 0.15 | J8: 0.15
B10: Notebook (Price per unit) | C10: 5 | D10: 5.2 | E10: 5.3 | F10: =E10*(1+F11) -> 5.3 | G10: =F10*(1+G11) -> 5.406 | H10: =G10*(1+H11) -> 5.51412 | I10: =H10*(1+I11) -> 5.6244024 | J10: =I10*(1+J11) -> 5.7368904
B11: % Growth | F11: 0 | G11: 0.02 | H11: 0.02 | I11: 0.02 | J11: 0.02
B13: Revenue Notebook ($ Million) | C13: =C7*C10 -> 1700 | D13: =D7*D10 -> 2033.2 | E13: =E7*E10 -> 2383.145 | F13: =F7*F10 -> 2502.3023 | G13: =G7*G10 -> 2935.2005 | H13: =H7*H10 -> 3442.9902 | I13: =I7*I10 -> 4038.6275 | J13: =J7*J10 -> 4737.3101 | K13: =C13/$C$34 -> 0.58521002
K14: =C14/$C$34 -> 0
B15: Segment 2 - Writing Pads | K15: =C15/$C$34 -> 0
B16: Writing Pads (Million Units) | C16: 221.5838 | D16: 234.87883 | E16: 246.62277 | F16: =E16*(1+F17) -> 251.55522 | G16: =F16*(1+G17) -> 266.64854 | H16: =G16*(1+H17) -> 282.64745 | I16: =H16*(1+I17) -> 299.6063 | J16: =I16*(1+J17) -> 317.58268 | K16: =C16/$C$34 -> 0.076278271
B17: % Growth | D17: =D16/C16-1 -> 0.06 | E17: =E16/D16-1 -> 0.05 | F17: 0.02 | G17: 0.06 | H17: 0.06 | I17: 0.06 | J17: 0.06 | K17: =C17/$C$34 -> 0
K18: =C18/$C$34 -> 0
B19: Writing Pads (Price per unit) | C19: 2 | D19: 2.1 | E19: 2.2 | F19: =E19*(1+F20) -> 2.2 | G19: =F19*(1+G20) -> 2.31 | H19: =G19*(1+H20) -> 2.4255 | I19: =H19*(1+I20) -> 2.546775 | J19: =I19*(1+J20) -> 2.6741138 | K19: =C19/$C$34 -> 0.00068848238
B20: % Growth | D20: =D19/C19-1 -> 0.05 | E20: =E19/D19-1 -> 0.047619048 | F20: 0 | G20: 0.05 | H20: 0.05 | I20: 0.05 | J20: 0.05 | K20: =C20/$C$34 -> 0
K21: =C21/$C$34 -> 0
B22: Writing Pads ($ Million) | C22: =C16*C19 -> 443.1676 | D22: =D16*D19 -> 493.24554 | E22: =E16*E19 -> 542.57009 | F22: =F16*F19 -> 553.42149 | G22: =G16*G19 -> 615.95812 | H22: =H16*H19 -> 685.56139 | I22: =I16*I19 -> 763.02983 | J22: =J16*J19 -> 849.2522 | K22: =C22/$C$34 -> 0.15255654
K23: =C23/$C$34 -> 0
K24: =C24/$C$34 -> 0
B25: Segment 3 - Premium Journals | K25: =C25/$C$34 -> 0
B26: Premium Journal (Million Units) | C26: 76.17724 | D26: 80.141315 | E26: 86.103742 | F26: =E26*(1+F27) -> 88.686854 | G26: =F26*(1+G27) -> 94.894934 | H26: =G26*(1+H27) -> 101.53758 | I26: =H26*(1+I27) -> 108.64521 | J26: =I26*(1+J27) -> 116.25037 | K26: =C26/$C$34 -> 0.026223344
B27: % Growth | F27: 0.03 | G27: 0.07 | H27: 0.07 | I27: 0.07 | J27: 0.07 | K27: =C27/$C$34 -> 0
K28: =C28/$C$34 -> 0
B29: Premium Journal (Pricer per unit) | C29: 10 | D29: 11 | E29: 12 | F29: =E29*(1+F30) -> 12 | G29: =F29*(1+G30) -> 13.2 | H29: =G29*(1+H30) -> 14.52 | I29: =H29*(1+I30) -> 15.972 | J29: =I29*(1+J30) -> 17.5692 | K29: =C29/$C$34 -> 0.0034424119
B30: % Growth | F30: 0 | G30: 0.1 | H30: 0.1 | I30: 0.1 | J30: 0.1 | K30: =C30/$C$34 -> 0
K31: =C31/$C$34 -> 0
B32: Premium Journal ($ Million) | C32: =C26*C29 -> 761.7724 | D32: =D26*D29 -> 881.55447 | E32: =E26*E29 -> 1033.2449 | F32: =F26*F29 -> 1064.2423 | G32: =G26*G29 -> 1252.6131 | H32: =H26*H29 -> 1474.3257 | I32: =I26*I29 -> 1735.2813 | J32: =J26*J29 -> 2042.4261 | K32: =C32/$C$34 -> 0.26223344
B34: Total Revenue ($ Million) | C34: =C32+C22+C13 -> 2904.94 | D34: =D32+D22+D13 -> 3408 | E34: =E32+E22+E13 -> 3958.96 | F34: =F32+F22+F13 -> 4119.966 | G34: =G32+G22+G13 -> 4803.7718 | H34: =H32+H22+H13 -> 5602.8773 | I34: =I32+I22+I13 -> 6536.9387 | J34: =J32+J22+J13 -> 7628.9884
B39: Cost of Sales Forecast
B40: COGS
B41: Notebook | C41: 799 | D41: 975.936 | E41: 1239.2354 | F41: =F13*F42 -> 1376.2662 | G41: =G13*G42 -> 1614.3603 | H41: =H13*H42 -> 1893.6446 | I41: =I13*I42 -> 2221.2451 | J41: =J13*J42 -> 2605.5206
B42: Segmental Gross Margin (%) | C42: =C41/C13 -> 0.47 | D42: =D41/D13 -> 0.48 | E42: =E41/E13 -> 0.52 | F42: 0.55 | G42: 0.55 | H42: 0.55 | I42: 0.55 | J42: 0.55
B44: Writing Pads | C44: 257.03721 | D44: 295.94732 | E44: 339.10631 | F44: =F22*F45 -> 359.72397 | G44: =G22*G45 -> 400.37278 | H44: =H22*H45 -> 445.6149 | I44: =I22*I45 -> 495.96939 | J44: =J22*J45 -> 552.01393
B45: Segmental Gross Margin (%) | C45: =C44/C22 -> 0.58 | D45: =D44/D22 -> 0.6 | E45: =E44/E22 -> 0.625 | F45: 0.65 | G45: 0.65 | H45: 0.65 | I45: 0.65 | J45: 0.65
B47: Premium Journals | C47: 438.79942 | D47: 594.24128 | E47: 731.38547 | F47: =F32*F48 -> 766.25442 | G47: =G32*G48 -> 901.88145 | H47: =H32*H48 -> 1061.5145 | I47: =I32*I48 -> 1249.4025 | J47: =J32*J48 -> 1470.5468
B48: Segmental Gross Margin (%) | C48: =C47/C32 -> 0.57602431 | D48: =D47/D32 -> 0.67408346 | E48: =E47/E32 -> 0.70785296 | F48: 0.72 | G48: 0.72 | H48: 0.72 | I48: 0.72 | J48: 0.72
B50: Total Cost of Sales | C50: =C47+C44+C41 -> 1494.8366 | D50: =D47+D44+D41 -> 1866.1246 | E50: =E47+E44+E41 -> 2309.7272 | F50: =F47+F44+F41 -> 2502.2446 | G50: =G47+G44+G41 -> 2916.6145 | H50: =H47+H44+H41 -> 3400.774 | I50: =I47+I44+I41 -> 3966.6171 | J50: =J47+J44+J41 -> 4628.0813
C51: 1494.8366 | D51: 1866.1246 | E51: 2309.7272
B54: SG&A Expenses
B56: Notebook | C56: 187 | D56: 227.7184 | E56: 262.14595 | F56: =F13*F57 -> 275.25325 | G56: =G13*G57 -> 322.87206 | H56: =H13*H57 -> 378.72893 | I56: =I13*I57 -> 444.24903 | J56: =J13*J57 -> 521.10411
B57: SG&A Expenses as a % of Notebook Sales | C57: =C56/$C$34 -> 0.064373102 | D57: =D56/D34 -> 0.066818779 | E57: =E56/E34 -> 0.066215862 | F57: 0.11 | G57: 0.11 | H57: 0.11 | I57: 0.11 | J57: 0.11
B59: Writing Pads | C59: 41.96531 | D59: 63.597809 | E59: 61.932162 | F59: =F22*F60 -> 60.876364 | G59: =G22*G60 -> 67.755394 | H59: =H22*H60 -> 75.411753 | I59: =I22*I60 -> 83.933281 | J59: =J22*J60 -> 93.417742
B60: SG&A Expenses as a % of Writing Pad Sales | C60: =C59/$C$34 -> 0.014446188 | D60: =D59/$C$34 -> 0.021892985 | E60: =E59/$C$34 -> 0.021319601 | F60: 0.11 | G60: 0.11 | H60: 0.11 | I60: 0.11 | J60: 0.11
B62: Premium Journals | C62: 76.17724 | D62: 96.970991 | E62: 123.98939 | F62: =F32*F63 -> 127.70907 | G62: =G32*G63 -> 150.31358 | H62: =H32*H63 -> 176.91908 | I62: =I32*I63 -> 208.23376 | J62: =J32*J63 -> 245.09113
B63: SG&A Expenses as a % of Premium Journal Sales | C63: =C62/$C$34 -> 0.026223344 | D63: =D62/$C$34 -> 0.033381409 | E63: =E62/$C$34 -> 0.042682255 | F63: 0.12 | G63: 0.12 | H63: 0.12 | I63: 0.12 | J63: 0.12
B65: SG&A Expense | C65: =C62+C59+C56 -> 305.14255 | D65: =D62+D59+D56 -> 388.2872 | E65: =E62+E59+E56 -> 448.0675 | F65: =F62+F59+F56 -> 463.83868 | G65: =G62+G59+G56 -> 540.94103 | H65: =H62+H59+H56 -> 631.05976 | I65: =I62+I59+I56 -> 736.41607 | J65: =J62+J59+J56 -> 859.61298

Sheet Depreciation Capex Forecast
A1: Big Books Company
B2: Depreciation Capex Forecast
C3: Actuals | F3: Forecast
B4: ($ in Million Except Per Share Amounts) | C4: Historical 1 | D4: Historical 2 | E4: Historical 3 | F4: Forecast 1 | G4: Forecast 2 | H4: Forecast 3 | I4: Forecast 4 | J4: Forecast 5
B6: Gross PPE
B7: Land | C7: ='Balance Sheet'!C16 -> 30 | D7: ='Balance Sheet'!D16 -> 30 | E7: ='Balance Sheet'!E16 -> 30 | F7: =E7+F15 -> 30 | G7: =F7+G15 -> 30 | H7: =G7+H15 -> 30 | I7: =H7+I15 -> 30 | J7: =I7+J15 -> 30
B8: Machinery and equipment | C8: ='Balance Sheet'!C17 -> 630 | D8: ='Balance Sheet'!D17 -> 700 | E8: ='Balance Sheet'!E17 -> 875 | F8: =E8+F16 -> 1080.9983 | G8: =F8+G16 -> 1321.1869 | H8: =G8+H16 -> 1601.3308 | I8: =H8+I16 -> 1928.1777 | J8: =I8+J16 -> 2309.6271
B9: Automobiles and trucks | C9: ='Balance Sheet'!C18 -> 250 | D9: ='Balance Sheet'!D18 -> 325 | E9: ='Balance Sheet'!E18 -> 400 | F9: =E9+F17 -> 482.39932 | G9: =F9+G17 -> 578.47476 | H9: =G9+H17 -> 690.5323 | I9: =H9+I17 -> 821.27107 | J9: =I9+J17 -> 973.85084
B10: Total | C10: =SUM(C7:C9) -> 910 | D10: =SUM(D7:D9) -> 1055 | E10: =SUM(E7:E9) -> 1305 | F10: =SUM(F7:F9) -> 1593.3976 | G10: =SUM(G7:G9) -> 1929.6616 | H10: =SUM(H7:H9) -> 2321.8631 | I10: =SUM(I7:I9) -> 2779.4488 | J10: =SUM(J7:J9) -> 3313.4779
B12: Net Sales | C12: ='Income Statement'!C5 -> 2904.94 | D12: ='Income Statement'!D5 -> 3408 | E12: ='Income Statement'!E5 -> 3958.96 | F12: ='Income Statement'!F5 -> 4119.966 | G12: ='Income Statement'!G5 -> 4803.7718 | H12: ='Income Statement'!H5 -> 5602.8773 | I12: ='Income Statement'!I5 -> 6536.9387 | J12: ='Income Statement'!J5 -> 7628.9884
B14: Capital Expenditure by Segment
B15: Land | D15: =D7-C7 -> 0 | E15: =E7-D7 -> 0 | F15: =F12*F21 -> 0 | G15: =G12*G21 -> 0 | H15: =H12*H21 -> 0 | I15: =I12*I21 -> 0 | J15: =J12*J21 -> 0
B16: Machinery and equipment | D16: =D8-C8 -> 70 | E16: =E8-D8 -> 175 | F16: =F12*F22 -> 205.9983 | G16: =G12*G22 -> 240.18859 | H16: =H12*H22 -> 280.14386 | I16: =I12*I22 -> 326.84693 | J16: =J12*J22 -> 381.44942
B17: Automobiles and trucks | D17: =D9-C9 -> 75 | E17: =E9-D9 -> 75 | F17: =F12*F23 -> 82.39932 | G17: =G12*G23 -> 96.075436 | H17: =H12*H23 -> 112.05755 | I17: =I12*I23 -> 130.73877 | J17: =J12*J23 -> 152.57977
B18: Total | D18: =SUM(D15:D17) -> 145 | E18: =SUM(E15:E17) -> 250 | F18: =SUM(F15:F17) -> 288.39762 | G18: =SUM(G15:G17) -> 336.26403 | H18: =SUM(H15:H17) -> 392.20141 | I18: =SUM(I15:I17) -> 457.58571 | J18: =SUM(J15:J17) -> 534.02919
B20: Capital Expenditure as % Net Sales (By Segment)
B21: Land | D21: =D15/$D$12 -> 0 | E21: =E15/$E$12 -> 0 | F21: 0 | G21: 0 | H21: 0 | I21: 0 | J21: 0
B22: Machinery and equipment | D22: =D16/$D$12 -> 0.020539906 | E22: =E16/$E$12 -> 0.044203528 | F22: 0.05 | G22: 0.05 | H22: 0.05 | I22: 0.05 | J22: 0.05
B23: Automobiles and trucks | D23: =D17/$D$12 -> 0.022007042 | E23: =E17/$E$12 -> 0.018944369 | F23: 0.02 | G23: 0.02 | H23: 0.02 | I23: 0.02 | J23: 0.02
B24: Gross PPE
B26: Calculating Depreciation
B28: Machinery & Equipments
B29: Useful Life | C29: 10 | D29: Years | F29: 1 | G29: 2 | H29: 3 | I29: 4 | J29: 5
B30: Machinery & Equipments | C30: =E8 -> 875 | D30: last year machineary | F30: =$C30/$C29 -> 87.5 | G30: =$C30/$C29 -> 87.5 | H30: =$C30/$C29 -> 87.5 | I30: =$C30/$C29 -> 87.5 | J30: =$C30/$C29 -> 87.5
B31: Depreciation Expense (existing)
C33: Capex | D33: Useful Life
B34: Forecast 1 | C34: {=TRANSPOSE(F16:J16)} -> 205.9983 | D34: 12 | E34: Years | F34: =$C34/$D34 -> 17.166525 | G34: =$C34/$D34 -> 17.166525 | H34: =$C34/$D34 -> 17.166525 | I34: =$C34/$D34 -> 17.166525 | J34: =$C34/$D34 -> 17.166525
B35: Forecast 2 | C35: 240.18859 | D35: 12 | G35: =$C35/$D35 -> 20.015716 | H35: =$C35/$D35 -> 20.015716 | I35: =$C35/$D35 -> 20.015716 | J35: =$C35/$D35 -> 20.015716
B36: Forecast 3 | C36: 280.14386 | D36: 12 | H36: =$C36/$D36 -> 23.345322 | I36: =$C36/$D36 -> 23.345322 | J36: =$C36/$D36 -> 23.345322
B37: Forecast 4 | C37: 326.84693 | D37: 12 | I37: =$C37/$D37 -> 27.237244 | J37: =$C37/$D37 -> 27.237244
B38: Forecast 5 | C38: 381.44942 | D38: 12 | J38: =$C38/$D38 -> 31.787452
B40: Total Depreciation (Machinery & Equipments) | F40: =SUM(F30:F39) -> 104.66652 | G40: =SUM(G30:G39) -> 124.68224 | H40: =SUM(H30:H39) -> 148.02756 | I40: =SUM(I30:I39) -> 175.26481 | J40: =SUM(J30:J39) -> 207.05226
B42: Automobiles & Trucks
B43: Useful Life | C43: 10 | D43: Years | F43: 1 | G43: 2 | H43: 3 | I43: 4 | J43: 5
B44: Automobiles & Trucks | C44: =E9 -> 400 | D44: last year auto and transport | F44: =$C44/$C43 -> 40 | G44: =$C44/$C43 -> 40 | H44: =$C44/$C43 -> 40 | I44: =$C44/$C43 -> 40 | J44: =$C44/$C43 -> 40
B45: Depreciation Expense (existing)
C47: Capex | D47: Useful Life
B48: Forecast 1 | C48: {=TRANSPOSE(F17:J17)} -> 82.39932 | D48: 12 | F48: =$C48/$D48 -> 6.86661 | G48: =$C48/$D48 -> 6.86661 | H48: =$C48/$D48 -> 6.86661 | I48: =$C48/$D48 -> 6.86661 | J48: =$C48/$D48 -> 6.86661
B49: Forecast 2 | C49: 96.075436 | D49: 12 | G49: =$C49/$D49 -> 8.0062863 | H49: =$C49/$D49 -> 8.0062863 | I49: =$C49/$D49 -> 8.0062863 | J49: =$C49/$D49 -> 8.0062863
B50: Forecast 3 | C50: 112.05755 | D50: 12 | H50: =$C50/$D50 -> 9.3381288 | I50: =$C50/$D50 -> 9.3381288 | J50: =$C50/$D50 -> 9.3381288
B51: Forecast 4 | C51: 130.73877 | D51: 12 | I51: =$C51/$D51 -> 10.894898 | J51: =$C51/$D51 -> 10.894898
B52: Forecast 5 | C52: 152.57977 | D52: 12 | J52: =$C52/$D52 -> 12.714981
B54: Total Depreciation (Automobiles & Trucks) | F54: =SUM(F44:F53) -> 46.86661 | G54: =SUM(G44:G53) -> 54.872896 | H54: =SUM(H44:H53) -> 64.211025 | I54: =SUM(I44:I53) -> 75.105923 | J54: =SUM(J44:J53) -> 87.820904
B57: Total Depreciation Expense | C57: ='Income Statement'!C12 -> 101.9 | D57: ='Income Statement'!D12 -> 123.1 | E57: ='Income Statement'!E12 -> 140 | F57: =F54+F40 -> 151.53313 | G57: =G54+G40 -> 179.55514 | H57: =H54+H40 -> 212.23859 | I57: =I54+I40 -> 250.37073 | J57: =J54+J40 -> 294.87316

Sheet Working Capital Forecast
A1: Big Books Company
B2: Working Capital Forecast
C3: Actuals | F3: Forecast
B4: ($ in Million Except Per Share Amounts) | C4: Historical 1 | D4: Historical 2 | E4: Historical 3 | F4: Forecast 1 | G4: Forecast 2 | H4: Forecast 3 | I4: Forecast 4 | J4: Forecast 5
B6: Working Capital Balances
B7: Receivable | C7: ='Balance Sheet'!C9 -> 462.9 | D7: ='Balance Sheet'!D9 -> 473.7 | E7: ='Balance Sheet'!E9 -> 473 | F7: =F$17/F21 -> 474.07828 | G7: =G$17/G21 -> 552.76278 | H7: =H$17/H21 -> 644.71465 | I7: =I$17/I21 -> 752.19568 | J7: =J$17/J21 -> 877.8562
B8: Inventory | C8: ='Balance Sheet'!C10 -> 327 | D8: ='Balance Sheet'!D10 -> 350.2 | E8: ='Balance Sheet'!E10 -> 383.8 | F8: =F$18/F22 -> 411.32788 | G8: =G$18/G22 -> 479.44348 | H8: =H$18/H22 -> 559.03134 | I8: =I$18/I22 -> 652.04664 | J8: =J$18/J22 -> 760.78048
B9: Other Current Assets | C9: ='Balance Sheet'!C11 -> 87.4 | D9: ='Balance Sheet'!D11 -> 82.8 | E9: ='Balance Sheet'!E11 -> 83.5 | F9: =F17*F30 -> 82.39932 | G9: =G17*G30 -> 96.075436 | H9: =H17*H30 -> 112.05755 | I9: =I17*I30 -> 130.73877 | J9: =J17*J30 -> 152.57977
B10: Total Non Cash Current Assets | C10: =SUM(C7:C9) -> 877.3 | D10: =SUM(D7:D9) -> 906.7 | E10: =SUM(E7:E9) -> 940.3 | F10: =SUM(F7:F9) -> 967.80548 | G10: =SUM(G7:G9) -> 1128.2817 | H10: =SUM(H7:H9) -> 1315.8035 | I10: =SUM(I7:I9) -> 1534.9811 | J10: =SUM(J7:J9) -> 1791.2164
B12: Accounts Payable | C12: ='Balance Sheet'!C30 -> 206.4 | D12: ='Balance Sheet'!D30 -> 221.4 | E12: ='Balance Sheet'!E30 -> 279.1 | F12: =F$18/F23 -> 308.49591 | G12: =G$18/G23 -> 359.58261 | H12: =H$18/H23 -> 419.27351 | I12: =I$18/I23 -> 489.03498 | J12: =J$18/J23 -> 570.58536
B13: Accrued Liabilities | C13: ='Balance Sheet'!C31 -> 180.7 | D13: ='Balance Sheet'!D31 -> 161.3 | E13: ='Balance Sheet'!E31 -> 176.7 | F13: =F18*F31 -> 200.17957 | G13: =G18*G31 -> 233.32916 | H13: =H18*H31 -> 272.06192 | I13: =I18*I31 -> 317.32937 | J13: =J18*J31 -> 370.2465
B14: Other Current Liabilities | C14: ='Balance Sheet'!C32 -> 68.3 | D14: ='Balance Sheet'!D32 -> 62.8 | E14: ='Balance Sheet'!E32 -> 81.8 | F14: =F18*F32 -> 87.578562 | G14: =G18*G32 -> 102.08151 | H14: =H18*H32 -> 119.02709 | I14: =I18*I32 -> 138.8316 | J14: =J18*J32 -> 161.98284
B15: Total Non-Debt Current Liabilities | C15: =SUM(C12:C14) -> 455.4 | D15: =SUM(D12:D14) -> 445.5 | E15: =SUM(E12:E14) -> 537.6 | F15: =SUM(F12:F14) -> 596.25405 | G15: =SUM(G12:G14) -> 694.99328 | H15: =SUM(H12:H14) -> 810.36252 | I15: =SUM(I12:I14) -> 945.19594 | J15: =SUM(J12:J14) -> 1102.8147
B17: Net Sales | C17: ='Income Statement'!C5 -> 2904.94 | D17: ='Income Statement'!D5 -> 3408 | E17: ='Income Statement'!E5 -> 3958.96 | F17: ='Income Statement'!F5 -> 4119.966 | G17: ='Income Statement'!G5 -> 4803.7718 | H17: ='Income Statement'!H5 -> 5602.8773 | I17: ='Income Statement'!I5 -> 6536.9387 | J17: ='Income Statement'!J5 -> 7628.9884 | L17: Number of days assumption | M17: 365
B18: Cost of Sales | C18: ='Income Statement'!C6 -> 1494.8366 | D18: ='Income Statement'!D6 -> 1866.1246 | E18: ='Income Statement'!E6 -> 2309.7272 | F18: ='Income Statement'!F6 -> 2502.2446 | G18: ='Income Statement'!G6 -> 2916.6145 | H18: ='Income Statement'!H6 -> 3400.774 | I18: ='Income Statement'!I6 -> 3966.6171 | J18: ='Income Statement'!J6 -> 4628.0813
B20: Turnover Ratios
B21: Receivables turnover (Net Sales / Receivables) | C21: =C17/C7 -> 6.2755239 | D21: =D17/D7 -> 7.1944269 | E21: =E17/E7 -> 8.3698943 | F21: =$M$17/F25 -> 8.6904762 | G21: =$M$17/G25 -> 8.6904762 | H21: =$M$17/H25 -> 8.6904762 | I21: =$M$17/I25 -> 8.6904762 | J21: =$M$17/J25 -> 8.6904762
B22: Inventory turnover (Cost of Sales / Inventory) | C22: =C18/C8 -> 4.5713658 | D22: =D18/D8 -> 5.3287396 | E22: =E18/E8 -> 6.0180489 | F22: =$M$17/F26 -> 6.0833333 | G22: =$M$17/G26 -> 6.0833333 | H22: =$M$17/H26 -> 6.0833333 | I22: =$M$17/I26 -> 6.0833333 | J22: =$M$17/J26 -> 6.0833333
B23: Accounts Payables turnover (Cost of Sales / Accounts Payable) | C23: =C18/C12 -> 7.2424255 | D23: =D18/D12 -> 8.4287471 | E23: =E18/E12 -> 8.2756258 | F23: =$M$17/F27 -> 8.1111111 | G23: =$M$17/G27 -> 8.1111111 | H23: =$M$17/H27 -> 8.1111111 | I23: =$M$17/I27 -> 8.1111111 | J23: =$M$17/J27 -> 8.1111111
B25: Receivables collection period (365 / Receivables Turnover) | C25: =$M$17/C21 -> 58.162475 | D25: =$M$17/D21 -> 50.733715 | E25: =$M$17/E21 -> 43.608675 | F25: 42 | G25: 42 | H25: 42 | I25: 42 | J25: 42
B26: Inventory processing period (365 / Inventory Turnover) | C26: =$M$17/C22 -> 79.844846 | D26: =$M$17/D22 -> 68.496498 | E26: =$M$17/E22 -> 60.650886 | F26: 60 | G26: 60 | H26: 60 | I26: 60 | J26: 60
B27: Payment period (365 / Accounts Payable Turnover) | C27: =$M$17/C23 -> 50.397481 | D27: =$M$17/D23 -> 43.304182 | E27: =$M$17/E23 -> 44.105426 | F27: 45 | G27: 45 | H27: 45 | I27: 45 | J27: 45
B28: Cash Collection Cycle | C28: =C26+C25-C27 -> 87.60984 | D28: =D26+D25-D27 -> 75.92603 | E28: =E26+E25-E27 -> 60.154136 | F28: =F26+F25-F27 -> 57 | G28: =G26+G25-G27 -> 57 | H28: =H26+H25-H27 -> 57 | I28: =I26+I25-I27 -> 57 | J28: =J26+J25-J27 -> 57
B30: Other Current Assets (% of Net Sales) | C30: =C9/C17 -> 0.03008668 | D30: =D9/D17 -> 0.024295775 | E30: =E9/E17 -> 0.021091398 | F30: 0.02 | G30: 0.02 | H30: 0.02 | I30: 0.02 | J30: 0.02
B31: Accrued Liabilities (% of Cost of Sales) | C31: =C13/C18 -> 0.12088278 | D31: =D13/D18 -> 0.086435814 | E31: =E13/E18 -> 0.076502542 | F31: 0.08 | G31: 0.08 | H31: 0.08 | I31: 0.08 | J31: 0.08
B32: Other Current Liabilities (% of Cost of Sales) | C32: =C14/C18 -> 0.045690612 | D32: =D14/D18 -> 0.03365263 | E32: =E14/E18 -> 0.035415438 | F32: 0.035 | G32: 0.035 | H32: 0.035 | I32: 0.035 | J32: 0.035
B34: Cash Flow from Individual line items
B35: Receivable | F35: =-(F7-E7) -> -1.078279 | G35: =-(G7-F7) -> -78.684503 | H35: =-(H7-G7) -> -91.951864 | I35: =-(I7-H7) -> -107.48104 | J35: =-(J7-I7) -> -125.66052
B36: Inventory | F36: =-(F8-E8) -> -27.527884 | G36: =-(G8-F8) -> -68.1156 | H36: =-(H8-G8) -> -79.587859 | I36: =-(I8-H8) -> -93.015299 | J36: =-(J8-I8) -> -108.73384
B37: Other Current Assets | F37: =-(F9-E9) -> 1.1006801 | G37: =-(G9-F9) -> -13.676116 | H37: =-(H9-G9) -> -15.98211 | I37: =-(I9-H9) -> -18.681228 | J37: =-(J9-I9) -> -21.840994
B38: Accounts Payable | F38: =F12-E12 -> 29.395913 | G38: =G12-F12 -> 51.0867 | H38: =H12-G12 -> 59.690894 | I38: =I12-H12 -> 69.761474 | J38: =J12-I12 -> 81.550381
B39: Accrued Liabilities | F39: =F13-E13 -> 23.47957 | G39: =G13-F13 -> 33.149592 | H39: =H13-G13 -> 38.732758 | I39: =I13-H13 -> 45.267445 | J39: =J13-I13 -> 52.917136
B40: Other Current Liabilities | F40: =F14-E14 -> 5.778562 | G40: =G14-F14 -> 14.502947 | H40: =H14-G14 -> 16.945582 | I40: =I14-H14 -> 19.804507 | J40: =J14-I14 -> 23.151247
B41: (Incease)/ Decrease in Working Capital | F41: =SUM(F35:F40) -> 31.148562 | G41: =SUM(G35:G40) -> -61.73698 | H41: =SUM(H35:H40) -> -72.152599 | I41: =SUM(I35:I40) -> -84.344136 | J41: =SUM(J35:J40) -> -98.616588

Sheet Amortization Forecast
A1: Big Books Company
B2: Amortization Forecast
C3: Actuals | F3: Forecast
B4: ($ in Million Except Per Share Amounts) | C4: Historical 1 | D4: Historical 2 | E4: Historical 3 | F4: Forecast 1 | G4: Forecast 2 | H4: Forecast 3 | I4: Forecast 4 | J4: Forecast 5
B6: Net Sales | C6: ='Income Statement'!C5 -> 2904.94 | D6: ='Income Statement'!D5 -> 3408 | E6: ='Income Statement'!E5 -> 3958.96 | F6: ='Income Statement'!F5 -> 4119.966 | G6: ='Income Statement'!G5 -> 4803.7718 | H6: ='Income Statement'!H5 -> 5602.8773 | I6: ='Income Statement'!I5 -> 6536.9387 | J6: ='Income Statement'!J5 -> 7628.9884
B7: Additions to Intangibles | D7: =-'Cash Flow Statement'!D23 -> 26.466 | E7: =-'Cash Flow Statement'!E23 -> 30.735 | F7: =F6*F8 -> 32.959728 | G7: =G6*G8 -> 38.430174 | H7: =H6*H8 -> 44.823018 | I7: =I6*I8 -> 52.295509 | J7: =J6*J8 -> 61.031907
B8: Additions to Intangibles as % of Net Sales | D8: =D7/D6 -> 0.0077658451 | E8: =E7/E6 -> 0.0077634025 | F8: 0.008 | G8: 0.008 | H8: 0.008 | I8: 0.008 | J8: 0.008
B10: Beginning Net Intangibles | D10: =C13 -> 46.5 | E10: =D13 -> 62.3 | F10: =E13 -> 80 | G10: =F13 -> 99.663755 | H10: =G13 -> 120.95494 | I10: =H13 -> 144.15667 | J10: =I13 -> 169.60133
B11: Additions to Intangibles | D11: =D7 -> 26.466 | E11: =E7 -> 30.735 | F11: =F7 -> 32.959728 | G11: =G7 -> 38.430174 | H11: =H7 -> 44.823018 | I11: =I7 -> 52.295509 | J11: =J7 -> 61.031907
B12: (Amortization Expense) | D12: ='Income Statement'!D13 -> 10.666 | E12: ='Income Statement'!E13 -> 13.035 | F12: =F28 -> 13.295973 | G12: =G28 -> 17.13899 | H12: =H28 -> 21.621292 | I12: =I28 -> 26.850843 | J12: =J28 -> 32.954034
B13: Ending Net Intangibles | C13: ='Balance Sheet'!C24 -> 46.5 | D13: =D10+D11-D12 -> 62.3 | E13: =E10+E11-E12 -> 80 | F13: =F10+F11-F12 -> 99.663755 | G13: =G10+G11-G12 -> 120.95494 | H13: =H10+H11-H12 -> 144.15667 | I13: =I10+I11-I12 -> 169.60133 | J13: =J10+J11-J12 -> 197.67921
E15: From:
E16: Existing Intangibles
B17: Existing Net Intangibles, net | C17: =E13 -> 80 | E17: Years | F17: =$C17/$C18 -> 10 | G17: =$C17/$C18 -> 10 | H17: =$C17/$C18 -> 10 | I17: =$C17/$C18 -> 10 | J17: =$C17/$C18 -> 10
B18: Useful Life | C18: 8 | D18: Years
B19: Straight Line
C21: Intangibles | D21: Useful Life
B22: Forecast 1 | C22: {=TRANSPOSE(F11:J11)} -> 32.959728 | D22: 10 | E22: Years | F22: =$C22/$D22 -> 3.2959728 | G22: =$C22/$D22 -> 3.2959728 | H22: =$C22/$D22 -> 3.2959728 | I22: =$C22/$D22 -> 3.2959728 | J22: =$C22/$D22 -> 3.2959728
B23: Forecast 2 | C23: 38.430174 | D23: 10 | G23: =$C23/$D23 -> 3.8430174 | H23: =$C23/$D23 -> 3.8430174 | I23: =$C23/$D23 -> 3.8430174 | J23: =$C23/$D23 -> 3.8430174
B24: Forecast 3 | C24: 44.823018 | D24: 10 | H24: =$C24/$D24 -> 4.4823018 | I24: =$C24/$D24 -> 4.4823018 | J24: =$C24/$D24 -> 4.4823018
B25: Forecast 4 | C25: 52.295509 | D25: 10 | I25: =$C25/$D25 -> 5.2295509 | J25: =$C25/$D25 -> 5.2295509
B26: Forecast 5 | C26: 61.031907 | D26: 10 | J26: =$C26/$D26 -> 6.1031907
B28: Total Amortization Expense | F28: =SUM(F17:F27) -> 13.295973 | G28: =SUM(G17:G27) -> 17.13899 | H28: =SUM(H17:H27) -> 21.621292 | I28: =SUM(I17:I27) -> 26.850843 | J28: =SUM(J17:J27) -> 32.954034

Sheet Shareholder's Equity Forecast
A1: Big Books Company
B2: Shareholders Equity Forecast
C3: Actuals | F3: Forecast
B4: ($ in Million Except Per Share Amounts) | C4: Historical 1 | D4: Historical 2 | E4: Historical 3 | F4: Forecast 1 | G4: Forecast 2 | H4: Forecast 3 | I4: Forecast 4 | J4: Forecast 5
B6: Dividend Assumptions
B7: Total Dividends Paid | C7: ='Income Statement'!C28 -> 150 | D7: ='Income Statement'!D28 -> 190 | E7: ='Income Statement'!E28 -> 230 | F7: =F8*F9 -> 208.56379 | G7: =G8*G9 -> 247.03056 | H7: =H8*H9 -> 292.207 | I7: =I8*I9 -> 345.12036 | J7: =J8*J9 -> 406.59214
B8: Net Income | C8: ='Income Statement'!C21 -> 774.5861 | D8: ='Income Statement'!D21 -> 754.10834 | E8: ='Income Statement'!E21 -> 740.30492 | F8: ='Income Statement'!F21 -> 695.21265 | G8: ='Income Statement'!G21 -> 823.4352 | H8: ='Income Statement'!H21 -> 974.02334 | I8: ='Income Statement'!I21 -> 1150.4012 | J8: ='Income Statement'!J21 -> 1355.3071
B9: Dividend Payout Ratio | C9: =C7/C8 -> 0.19365181 | D9: =D7/D8 -> 0.25195319 | E9: =E7/E8 -> 0.31068279 | F9: 0.3 | G9: 0.3 | H9: 0.3 | I9: 0.3 | J9: 0.3
B12: Common Stock & APIC | C12: ='Balance Sheet'!C43 -> 1000 | D12: ='Balance Sheet'!D43 -> 1000 | E12: ='Balance Sheet'!E43 -> 1000 | F12: 1000 | G12: 1000 | H12: 1000 | I12: 1000 | J12: 1000
B13: Treasury Stock | C13: ='Balance Sheet'!C44 -> -1500 | D13: ='Balance Sheet'!D44 -> -1575 | E13: ='Balance Sheet'!E44 -> -1655 | F13: =E13+F19 -> -1755 | G13: =F13+G19 -> -1855 | H13: =G13+H19 -> -1955 | I13: =H13+I19 -> -2055 | J13: =I13+J19 -> -2155
B14: Retained Earnings | C14: ='Balance Sheet'!C45 -> 1000 | D14: ='Balance Sheet'!D45 -> 1564.1083 | E14: ='Balance Sheet'!E45 -> 2074.4133 | F14: =E14+F8-F7 -> 2561.0621 | G14: =F14+G8-G7 -> 3137.4668 | H14: =G14+H8-H7 -> 3819.2831 | I14: =H14+I8-I7 -> 4624.5639 | J14: =I14+J8-J7 -> 5573.2789
B15: Accumulated Other Comprehensive Income | C15: ='Balance Sheet'!C46 -> 0 | D15: ='Balance Sheet'!D46 -> 0 | E15: ='Balance Sheet'!E46 -> 0 | Q15: 1
B16: Shareholders Equity | C16: =SUM(C12:C15) -> 500 | D16: =SUM(D12:D15) -> 989.10834 | E16: =SUM(E12:E15) -> 1419.4133 | F16: =SUM(F12:F15) -> 1806.0621 | G16: =SUM(G12:G15) -> 2282.4668 | H16: =SUM(H12:H15) -> 2864.2831 | I16: =SUM(I12:I15) -> 3569.5639 | J16: =SUM(J12:J15) -> 4418.2789 | Q16: ?
B18: Stock Repurchases & Issuances:
B19: Stock Repurchases ($) | C19: -50 | D19: ='Cash Flow Statement'!D30 -> -75 | E19: ='Cash Flow Statement'!E30 -> -80 | F19: -100 | G19: -100 | H19: -100 | I19: -100 | J19: -100
B20: Shares Repurchased | C20: 0.79365079 | D20: 1.25 | E20: 1.3793103 | F20: =IFERROR(F19/F21,0) -> -1.7064779 | G20: =IFERROR(G19/G21,0) -> -1.419207 | H20: =IFERROR(H19/H21,0) -> -1.1845893 | I20: =IFERROR(I19/I21,0) -> -0.99218889 | J20: =IFERROR(J19/J21,0) -> -0.83448557
B21: Share Price | C21: =-C19/C20 -> 63 | D21: =-D19/D20 -> 60 | E21: =-E19/E20 -> 58 | F21: =F22*F23 -> 58.600232 | G21: =G22*G23 -> 70.461886 | H21: =H22*H23 -> 84.417441 | I21: =I22*I23 -> 100.78726 | J21: =J22*J23 -> 119.83431
B22: EPS | C22: ='Income Statement'!C26 -> 7.8047872 | D22: ='Income Statement'!D26 -> 7.6953757 | E22: ='Income Statement'!E26 -> 7.6623675 | F22: ='Income Statement'!F26 -> 7.325029 | G22: ='Income Statement'!G26 -> 8.8077357 | H22: ='Income Statement'!H26 -> 10.55218 | I22: ='Income Statement'!I26 -> 12.598408 | J22: ='Income Statement'!J26 -> 14.979288
B23: Repurchase PE Multiple | C23: =C21/C22 -> 8.071969 | D23: =D21/D22 -> 7.7968903 | E23: =E21/E22 -> 7.569462 | F23: 8 | G23: 8 | H23: 8 | I23: 8 | J23: 8
B25: Outstanding Shares | C25: ='Income Statement'!C24 -> 99.245 | D25: ='Income Statement'!D24 -> 97.995 | E25: ='Income Statement'!E24 -> 96.61569 | F25: =E25+F20 -> 94.909212 | G25: =F25+G20 -> 93.490005 | H25: =G25+H20 -> 92.305415 | I25: =H25+I20 -> 91.313227 | J25: =I25+J20 -> 90.478741
E35: `

Sheet Debt Forecast
A1: Big Books Company
B2: Debt Forecast
C3: Actuals | F3: Forecast
B4: ($ in Million Except Per Share Amounts) | C4: Historical 1 | D4: Historical 2 | E4: Historical 3 | F4: Forecast 1 | G4: Forecast 2 | H4: Forecast 3 | I4: Forecast 4 | J4: Forecast 5
B6: Cash Flow from Operations | F6: ='Cash Flow Statement'!F17 -> 891.97354 | G6: ='Cash Flow Statement'!G17 -> 964.77779 | H6: ='Cash Flow Statement'!H17 -> 1150.5262 | I6: ='Cash Flow Statement'!I17 -> 1366.2089 | J6: ='Cash Flow Statement'!J17 -> 1617.0918
B7: Cash Flow From Investing Activities | F7: ='Cash Flow Statement'!F24 -> -351.35735 | G7: ='Cash Flow Statement'!G24 -> -404.6942 | H7: ='Cash Flow Statement'!H24 -> -467.02443 | I7: ='Cash Flow Statement'!I24 -> -539.88122 | J7: ='Cash Flow Statement'!J24 -> -625.06109
B8: 1. Total Cash Available (Before Equity & Debt) | F8: =SUM(F6:F7) -> 540.61619 | G8: =SUM(G6:G7) -> 560.08359 | H8: =SUM(H6:H7) -> 683.50174 | I8: =SUM(I6:I7) -> 826.32772 | J8: =SUM(J6:J7) -> 992.03071
B10: Equity Items (Already Forecasted)
B11: Dividends | F11: =-'Shareholder''s Equity Forecast'!F7 -> -208.56379 | G11: =-'Shareholder''s Equity Forecast'!G7 -> -247.03056 | H11: =-'Shareholder''s Equity Forecast'!H7 -> -292.207 | I11: =-'Shareholder''s Equity Forecast'!I7 -> -345.12036 | J11: =-'Shareholder''s Equity Forecast'!J7 -> -406.59214
B12: Stock Repurchase | F12: ='Shareholder''s Equity Forecast'!F19 -> -100 | G12: ='Shareholder''s Equity Forecast'!G19 -> -100 | H12: ='Shareholder''s Equity Forecast'!H19 -> -100 | I12: ='Shareholder''s Equity Forecast'!I19 -> -100 | J12: ='Shareholder''s Equity Forecast'!J19 -> -100
B13: 2. Cash Flow Equity Items | F13: =SUM(F11:F12) -> -308.56379 | G13: =SUM(G11:G12) -> -347.03056 | H13: =SUM(H11:H12) -> -392.207 | I13: =SUM(I11:I12) -> -445.12036 | J13: =SUM(J11:J12) -> -506.59214
B15: Ensure Cash is NOT Negative
B16: Beginning Cash | F16: ='Balance Sheet'!E7 -> 48.713267 | G16: ='Balance Sheet'!F7 -> 30 | H16: ='Balance Sheet'!G7 -> -1.3209401 | I16: ='Balance Sheet'!H7 -> 119.53098 | J16: ='Balance Sheet'!I7 -> 443.85925
B17: Minimum Cash Balance | F17: 30 | G17: 31 | H17: 32 | I17: 33 | J17: 34
B18: 3. Cash Available (Required) | F18: =F16-F17 -> 18.713267 | G18: =G16-G17 -> -1 | H18: =H16-H17 -> -33.32094 | I18: =I16-I17 -> 86.530977 | J18: =J16-J17 -> 409.85925
B20: Net Cash Available for Debt Payments (1+2+3) | F20: =F8+F13+F18 -> 250.76567 | G20: =G8+G13+G18 -> 212.05303 | H20: =H8+H13+H18 -> 257.9738 | I20: =I8+I13+I18 -> 467.73833 | J20: =J8+J13+J18 -> 895.29782
B22: Long Term Debt Payments (committed) | F22: =F33 -> -300 | G22: =G33 -> -200 | H22: =H33 -> -100 | I22: =I33 -> -50 | J22: =J33 -> -50
B23: Net Cash Left for Revolving Credit | F23: =SUM(F20:F22) -> -49.234333 | G23: =SUM(G20:G22) -> 12.053028 | H23: =SUM(H20:H22) -> 157.9738 | I23: =SUM(I20:I22) -> 417.73833 | J23: =SUM(J20:J22) -> 845.29782
B25: Revolving Credit Facility
B26: Beginning Balance | F26: =E28 -> 101 | G26: =F28 -> 150.23433 | H26: =G28 -> 138.18131 | I26: =H28 -> 0 | J26: =I28 -> 0
B27: Discretionary (Paydown)/ Borrowings | F27: =IF(F23<0,-F23,-MIN(F26,F23)) -> 49.234333 | G27: =IF(G23<0,-G23,-MIN(G26,G23)) -> -12.053028 | H27: =IF(H23<0,-H23,-MIN(H26,H23)) -> -138.18131 | I27: =IF(I23<0,-I23,-MIN(I26,I23)) -> 0 | J27: =IF(J23<0,-J23,-MIN(J26,J23)) -> 0
B28: Ending Balance | C28: ='Balance Sheet'!C36 -> 250 | D28: ='Balance Sheet'!D36 -> 150 | E28: ='Balance Sheet'!E36 -> 101 | F28: =SUM(F26:F27) -> 150.23433 | G28: =SUM(G26:G27) -> 138.18131 | H28: =SUM(H26:H27) -> 0 | I28: =SUM(I26:I27) -> 0 | J28: =SUM(J26:J27) -> 0
B30: Long Term Debt
B31: Beginning Balance | F31: =E34 -> 1635 | G31: =F34 -> 1335 | H31: =G34 -> 1135 | I31: =H34 -> 1035 | J31: =I34 -> 985
B32: Issuance | F32: 0
B33: (Repayment/ Amortization) | F33: -300 | G33: -200 | H33: -100 | I33: -50 | J33: -50
B34: Ending Balance | C34: ='Balance Sheet'!C37 -> 2200 | D34: ='Balance Sheet'!D37 -> 1990 | E34: ='Balance Sheet'!E37 -> 1635 | F34: =SUM(F31:F33) -> 1335 | G34: =SUM(G31:G33) -> 1135 | H34: =SUM(H31:H33) -> 1035 | I34: =SUM(I31:I33) -> 985 | J34: =SUM(J31:J33) -> 935
B36: Forecasting Interest Expense
B38: 1. Revolving Credit Facility
B39: Average Revolving Credit Facility Outstanding | F39: =AVERAGE(E28:F28) -> 125.61717 | G39: =AVERAGE(F28:G28) -> 144.20782 | H39: =AVERAGE(G28:H28) -> 69.090653 | I39: =AVERAGE(H28:I28) -> 0 | J39: =AVERAGE(I28:J28) -> 0
B40: Interest Rate | F40: 0.05 | G40: 0.05 | H40: 0.05 | I40: 0.05 | J40: 0.05
B41: Interest Expense | F41: =F39*F40 -> 6.2808585 | G41: =G39*G40 -> 7.2103915 | H41: =H39*H40 -> 3.4545326 | I41: =I39*I40 -> 0 | J41: =J39*J40 -> 0
B43: 2. Long Term Debt
B44: Average Long Term Debt Oustanding | F44: =AVERAGE(E34:F34) -> 1485 | G44: =AVERAGE(F34:G34) -> 1235 | H44: =AVERAGE(G34:H34) -> 1085 | I44: =AVERAGE(H34:I34) -> 1010 | J44: =AVERAGE(I34:J34) -> 960
B45: Interest Rate | F45: 0.045 | G45: 0.045 | H45: 0.045 | I45: 0.045 | J45: 0.045
B46: Interest Expense | F46: =F44*F45 -> 66.825 | G46: =G44*G45 -> 55.575 | H46: =H44*H45 -> 48.825 | I46: =I44*I45 -> 45.45 | J46: =J44*J45 -> 43.2
B48: Total Interest Expense (1+2) | F48: =F46+F41 -> 73.105859 | G48: =G46+G41 -> 62.785391 | H48: =H46+H41 -> 52.279533 | I48: =I46+I41 -> 45.45 | J48: =J46+J41 -> 43.2
B50: Forecasting Interest Income
B52: 1. Cash & Cash Equivalents | D52: =AVERAGE('Balance Sheet'!C7:D7) -> 56.554171 | E52: =AVERAGE('Balance Sheet'!D7:E7) -> 67.160805 | F52: =AVERAGE('Balance Sheet'!E7:F7) -> 39.356634 | G52: =AVERAGE('Balance Sheet'!F7:G7) -> 14.33953 | H52: =AVERAGE('Balance Sheet'!G7:H7) -> 59.105018 | I52: =AVERAGE('Balance Sheet'!H7:I7) -> 281.69511 | J52: =AVERAGE('Balance Sheet'!I7:J7) -> 656.69242
B53: 2. Marketable Securities | D53: =AVERAGE('Balance Sheet'!C8:D8) -> 45 | E53: =AVERAGE('Balance Sheet'!D8:E8) -> 55 | F53: =AVERAGE('Balance Sheet'!E8:F8) -> 65 | G53: =AVERAGE('Balance Sheet'!F8:G8) -> 75 | H53: =AVERAGE('Balance Sheet'!G8:H8) -> 85 | I53: =AVERAGE('Balance Sheet'!H8:I8) -> 95 | J53: =AVERAGE('Balance Sheet'!I8:J8) -> 105
B54: 3. Long Term Securities | D54: =AVERAGE('Balance Sheet'!C14:D14) -> 170 | E54: =AVERAGE('Balance Sheet'!D14:E14) -> 190 | F54: =AVERAGE('Balance Sheet'!E14:F14) -> 210 | G54: =AVERAGE('Balance Sheet'!F14:G14) -> 230 | H54: =AVERAGE('Balance Sheet'!G14:H14) -> 250 | I54: =AVERAGE('Balance Sheet'!H14:I14) -> 270 | J54: =AVERAGE('Balance Sheet'!I14:J14) -> 290
B55: Total | D55: =SUM(D52:D54) -> 271.55417 | E55: =SUM(E52:E54) -> 312.1608 | F55: =SUM(F52:F54) -> 314.35663 | G55: =SUM(G52:G54) -> 319.33953 | H55: =SUM(H52:H54) -> 394.10502 | I55: =SUM(I52:I54) -> 646.69511 | J55: =SUM(J52:J54) -> 1051.6924
B57: Interest Income | D57: ='Income Statement'!D17 -> 9.4007832 | E57: ='Income Statement'!E17 -> 10.939602 | F57: =F55*F59 -> 11.002482 | G57: =G55*G59 -> 11.176884 | H57: =H55*H59 -> 13.793676 | I57: =I55*I59 -> 22.634329 | J57: =J55*J59 -> 36.809235
B59: Effective Interest Rate | D59: =D57/D55 -> 0.034618445 | E59: =E57/E55 -> 0.035044764 | F59: 0.035 | G59: 0.035 | H59: 0.035 | I59: 0.035 | J59: 0.035

Sheet Other Assets & Liabilities
A1: Big Books Company
B2: Other Assets and Liablities
C3: Actuals | F3: Forecast
B4: ($ in Million Except Per Share Amounts) | C4: Historical 1 | D4: Historical 2 | E4: Historical 3 | F4: Forecast 1 | G4: Forecast 2 | H4: Forecast 3 | I4: Forecast 4 | J4: Forecast 5
B6: Goodwill | C6: ='Balance Sheet'!C25 -> 1671.7 | D6: ='Balance Sheet'!D25 -> 1671.7 | E6: ='Balance Sheet'!E25 -> 1671.7 | F6: =E6 -> 1671.7 | G6: =F6 -> 1671.7 | H6: =G6 -> 1671.7 | I6: =H6 -> 1671.7 | J6: =I6 -> 1671.7
B7: Marketable Securities | C7: ='Balance Sheet'!C8 -> 40 | D7: ='Balance Sheet'!D8 -> 50 | E7: ='Balance Sheet'!E8 -> 60 | F7: =E7+10 -> 70 | G7: =F7+10 -> 80 | H7: =G7+10 -> 90 | I7: =H7+10 -> 100 | J7: =I7+10 -> 110
B8: Long Term Securities | C8: ='Balance Sheet'!C14 -> 160 | D8: ='Balance Sheet'!D14 -> 180 | E8: ='Balance Sheet'!E14 -> 200 | F8: =E8+20 -> 220 | G8: =F8+20 -> 240 | H8: =G8+20 -> 260 | I8: =H8+20 -> 280 | J8: =I8+20 -> 300
B9: Other Long Term Liabilities | C9: ='Balance Sheet'!C40 -> 153 | D9: ='Balance Sheet'!D40 -> 157.3 | E9: ='Balance Sheet'!E40 -> 187.1 | F9: =E9 -> 187.1 | G9: =F9 -> 187.1 | H9: =G9 -> 187.1 | I9: =H9 -> 187.1 | J9: =I9 -> 187.1
B10: Post retirement Pension Cost | C10: ='Balance Sheet'!C41 -> 72.7 | D10: ='Balance Sheet'!D41 -> 54.4 | E10: ='Balance Sheet'!E41 -> 60.6 | F10: =E10 -> 60.6 | G10: =F10 -> 60.6 | H10: =G10 -> 60.6 | I10: =H10 -> 60.6 | J10: =I10 -> 60.6

Sheet Relative Valuations
A1: Big Books Company
B2: Relative Valuations
I3: Multiples | M3: Multiples | Q3: Multiples
I4: EV/Revenue | M4: EV/EBITDA | Q4: Price / Earnings (P/E)
B5: Company | C5: Ticker | E5: Price | F5: MarketCap | G5: EV | I5: Historical 3 | J5: Forecast 1 | K5: Forecast 2 | M5: Historical 3 | N5: Forecast 1 | O5: Forecast 2 | Q5: Historical 3 | R5: Forecast 1 | S5: Forecast 2
B6: Athen Books | C6: ABS | E6: 175.5 | F6: 7094.9452 | G6: 2538.9165 | I6: 5.4601589 | J6: 5.9962291 | K6: 5.6886036 | M6: 19.349438 | N6: 23.712495 | O6: 23.351589 | Q6: 26.259952 | R6: 38.162275 | S6: 39.125238
B7: Bazaar Books | C7: BZS | E7: 8.49 | F7: 652.7746 | G7: 208.56066 | I7: 1.69115 | J7: 1.9273594 | K7: 1.8284797 | M7: 5.993013 | N7: 7.6218735 | O7: 7.505868 | Q7: 8.1333747 | R7: 12.266446 | S7: 12.575969
B8: Focus Books | C8: FBS | E8: 56.97 | F8: 1550.5081 | G8: 515.67848 | I8: 6.3474141 | J8: 6.6386822 | K8: 6.2980969 | M8: 22.493649 | N8: 26.25312 | O8: 25.853545 | Q8: 30.527095 | R8: 42.25109 | S8: 43.317228
B9: BroadSoft Publishing | C9: BPS | E9: 27.85 | F9: 842.40198 | G9: 269.64734 | I9: 2.1164383 | J9: 2.3556614 | K9: 2.2348086 | M9: 7.5001281 | N9: 9.3156231 | O9: 9.1738386 | Q9: 10.178745 | R9: 14.992322 | S9: 15.370629
B10: Concur Publishing | C10: CPS | E10: 105.82 | F10: 6351.9451 | G10: 2156.2286 | I10: 4.755602 | J10: 5.139625 | K10: 4.875946 | M10: 16.852665 | N10: 20.324996 | O10: 20.015648 | Q10: 22.871473 | R10: 32.710522 | S10: 33.535918
B11: Contact Books | C11: CBS | E11: 26.805 | F11: 878.43878 | G11: 264.33322 | I11: 1.315628 | J11: 1.4990573 | K11: 1.4221509 | M11: 4.6622569 | N11: 5.9281238 | O11: 5.8378973 | Q11: 6.3273486 | R11: 9.5405688 | S11: 9.7813094
B12: OnDemand books | C12: ODB | E12: 56.12 | F12: 3243.8281 | G12: 1104.0117 | I12: 6.722108 | J12: 6.4245312 | K12: 6.0949325 | M12: 23.82147 | N12: 25.406245 | O12: 25.01956 | Q12: 32.329138 | R12: 40.888152 | S12: 41.919898
B13: Pocket Books | C13: PBS | E13: 73.89 | F13: 2912.5359 | G13: 923.03012 | I13: 10.678756 | J13: 10.707552 | K13: 10.158221 | M13: 37.842843 | N13: 42.343741 | O13: 41.699267 | Q13: 51.358144 | R13: 68.14692 | S13: 69.866496
B14: Open Publishing | C14: OPS | E14: 25.63 | F14: 783.69705 | G14: 271.73477 | I14: 1.9074868 | J14: 2.1415104 | K14: 2.0316442 | M14: 6.7596565 | N14: 8.4687483 | O14: 8.3398533 | Q14: 9.1738195 | R14: 13.629384 | S14: 13.973299
B15: Group Publishing House | C15: GPH | E15: 35.57 | F15: 1416.0951 | G15: 455.93592 | I15: 3.2005171 | J15: 3.4264166 | K15: 3.2506307 | M15: 11.341832 | N15: 13.549997 | O15: 13.343765 | Q15: 15.392487 | R15: 21.807014 | S15: 22.357279
B17: Median | E17: =MEDIAN(E6:E15) -> 45.845 | F17: =MEDIAN(F6:F15) -> 1483.3016 | G17: =MEDIAN(G6:G15) -> 485.8072 | I17: =MEDIAN(I6:I15) -> 3.9780595 | J17: =MEDIAN(J6:J15) -> 4.2830208 | K17: =MEDIAN(K6:K15) -> 4.0632883 | M17: =MEDIAN(M6:M15) -> 14.097249 | N17: =MEDIAN(N6:N15) -> 16.937497 | O17: =MEDIAN(O6:O15) -> 16.679707 | Q17: =MEDIAN(Q6:Q15) -> 19.13198 | R17: =MEDIAN(R6:R15) -> 27.258768 | S17: =MEDIAN(S6:S15) -> 27.946598
B18: Mean | E18: =AVERAGE(E6:E15) -> 59.2645 | F18: =AVERAGE(F6:F15) -> 2572.717 | G18: =AVERAGE(G6:G15) -> 870.80773 | I18: =AVERAGE(I6:I15) -> 4.419526 | J18: =AVERAGE(J6:J15) -> 4.6256625 | K18: =AVERAGE(K6:K15) -> 4.3883514 | M18: =AVERAGE(M6:M15) -> 15.661695 | N18: =AVERAGE(N6:N15) -> 18.292496 | O18: =AVERAGE(O6:O15) -> 18.014083 | Q18: =AVERAGE(Q6:Q15) -> 21.255158 | R18: =AVERAGE(R6:R15) -> 29.439469 | S18: =AVERAGE(S6:S15) -> 30.182326
B19: Low | E19: =MIN(E6:E15) -> 8.49 | F19: =MIN(F6:F15) -> 652.7746 | G19: =MIN(G6:G15) -> 208.56066 | I19: =MIN(I6:I15) -> 1.315628 | J19: =MIN(J6:J15) -> 1.4990573 | K19: =MIN(K6:K15) -> 1.4221509 | M19: =MIN(M6:M15) -> 4.6622569 | N19: =MIN(N6:N15) -> 5.9281238 | O19: =MIN(O6:O15) -> 5.8378973 | Q19: =MIN(Q6:Q15) -> 6.3273486 | R19: =MIN(R6:R15) -> 9.5405688 | S19: =MIN(S6:S15) -> 9.7813094
B20: High | E20: =MAX(E6:E15) -> 175.5 | F20: =MAX(F6:F15) -> 7094.9452 | G20: =MAX(G6:G15) -> 2538.9165 | I20: =MAX(I6:I15) -> 10.678756 | J20: =MAX(J6:J15) -> 10.707552 | K20: =MAX(K6:K15) -> 10.158221 | M20: =MAX(M6:M15) -> 37.842843 | N20: =MAX(N6:N15) -> 42.343741 | O20: =MAX(O6:O15) -> 41.699267 | Q20: =MAX(Q6:Q15) -> 51.358144 | R20: =MAX(R6:R15) -> 68.14692 | S20: =MAX(S6:S15) -> 69.866496
B23: EV to Revenue
B25: Big Books Valuations | D25: Current Year
C26: Histroical 3 | D26: Forecast 1 | E26: Forecast 2
B27: Industry EV/Revenue | C27: =I18 -> 4.419526 | D27: =J18 -> 4.6256625 | E27: =K18 -> 4.3883514
B28: Big Books Revenue | C28: ='Income Statement'!E5 -> 3958.96 | D28: ='Income Statement'!F5 -> 4119.966 | E28: ='Income Statement'!G5 -> 4803.7718
B29: EV | C29: =C27*C28 -> 17496.726 | D29: =D27*D28 -> 19057.572 | E29: =E27*E28 -> 21080.639
B31: Debt | C31: ='Balance Sheet'!$E$38 -> 1736 | D31: ='Balance Sheet'!$F$38 -> 1485.4693 | E31: ='Balance Sheet'!$G$38 -> 1273.1813
B32: Cash & Cash Equivalents | C32: ='Balance Sheet'!$E$7 -> 48.713267 | D32: ='Balance Sheet'!$F$7 -> 30 | E32: ='Balance Sheet'!$G$7 -> -1.3209401
B33: Marketable Securities | C33: ='Balance Sheet'!$E$8 -> 60 | D33: ='Balance Sheet'!$F$8 -> 70 | E33: ='Balance Sheet'!$G$8 -> 80
B34: Long Term Securities | C34: ='Balance Sheet'!$E$14 -> 200 | D34: ='Balance Sheet'!$F$14 -> 220 | E34: ='Balance Sheet'!$G$14 -> 240
B35: Equity Value | C35: =C29+C32-C31+C33+C34 -> 16069.44 | D35: =D29+D32-D31+D33+D34 -> 17892.103 | E35: =E29+E32-E31+E33+E34 -> 20126.136
B36: NO of O/S Shares | C36: ='Income Statement'!$E$24 -> 96.61569 | D36: ='Income Statement'!$F$24 -> 94.909212 | E36: ='Income Statement'!$G$24 -> 93.490005
B37: Price Per Share | C37: =C35/C36 -> 166.32329 | D37: =D35/D36 -> 188.51808 | E37: =E35/E36 -> 215.27581
B41: EV to EBITDA
B43: Big Books Valuations | D43: Current Year
C44: Histroical 3 | D44: Forecast 1 | E44: Forecast 2
B45: Industry EV/EBITDA | C45: =M18 -> 15.661695 | D45: =N18 -> 18.292496 | E45: =O18 -> 18.014083
B46: Big Books EBITDA | C46: ='Income Statement'!E10 -> 1201.1653 | D46: ='Income Statement'!F10 -> 1153.8827 | E46: ='Income Statement'!G10 -> 1346.2162
B47: EV | C47: =C46*C45 -> 18812.285 | D47: =D46*D45 -> 21107.395 | E47: =E46*E45 -> 24250.851
B49: Debt | C49: ='Balance Sheet'!$E$38 -> 1736 | D49: ='Balance Sheet'!$F$38 -> 1485.4693 | E49: ='Balance Sheet'!$G$38 -> 1273.1813
B50: Cash & Cash Equivalents | C50: ='Balance Sheet'!$E$7 -> 48.713267 | D50: ='Balance Sheet'!$F$7 -> 30 | E50: ='Balance Sheet'!$G$7 -> -1.3209401
B51: Marketable Securities | C51: ='Balance Sheet'!$E$8 -> 60 | D51: ='Balance Sheet'!$F$8 -> 70 | E51: ='Balance Sheet'!$G$8 -> 80
B52: Long Term Securities | C52: ='Balance Sheet'!$E$14 -> 200 | D52: ='Balance Sheet'!$F$14 -> 220 | E52: ='Balance Sheet'!$G$14 -> 240
B53: Equity Value | C53: =C47+C50-C49+C51+C52 -> 17384.998 | D53: =D47+D50-D49+D51+D52 -> 19941.925 | E53: =E47+E50-E49+E51+E52 -> 23296.349
B54: NO of O/S Shares | C54: ='Income Statement'!$E$24 -> 96.61569 | D54: ='Income Statement'!$F$24 -> 94.909212 | E54: ='Income Statement'!$G$24 -> 93.490005
B55: Price Per Share | C55: =C53/C54 -> 179.9397 | D55: =D53/D54 -> 210.1158 | E55: =E53/E54 -> 249.18545
B58: Price to Earnings Ratio
B60: Big Books Valuations | D60: Current Year
C61: Histroical 3 | D61: Forecast 1 | E61: Forecast 2
B62: Industry PE Ratio | C62: =Q18 -> 21.255158 | D62: =R18 -> 29.439469 | E62: =S18 -> 30.182326
B63: Big Books EPS | C63: ='Income Statement'!E26 -> 7.6623675 | D63: ='Income Statement'!F26 -> 7.325029 | E63: ='Income Statement'!G26 -> 8.8077357
B64: Price Per Share | C64: =C62*C63 -> 162.86483 | D64: =D62*D63 -> 215.64497 | E64: =E62*E63 -> 265.83795

Sheet DCF Valuations
A1: Big Books Company
B2: DCF Valuations
C3: Actuals | F3: Forecast
B4: ($ in Million Except Per Share Amounts) | C4: Historial 1 | D4: Historial 2 | E4: Historial 3 | F4: Forecast 1 | G4: Forecast 2 | H4: Forecast 3 | I4: Forecast 4 | J4: Forecast 5
B6: EBIT | F6: ='Income Statement'!F14 -> 989.05358 | G6: ='Income Statement'!G14 -> 1149.5221 | H6: ='Income Statement'!H14 -> 1337.1836 | I6: ='Income Statement'!I14 -> 1556.684 | J6: ='Income Statement'!J14 -> 1813.4669
B8: Free Cash Flow to Firm
B9: EBIT x (1-t) | F9: =F6*(1-'Income Statement'!F23) -> 741.79018 | G9: =G6*(1-'Income Statement'!G23) -> 862.14158 | H9: =H6*(1-'Income Statement'!H23) -> 1002.8877 | I9: =I6*(1-'Income Statement'!I23) -> 1167.513 | J9: =J6*(1-'Income Statement'!J23) -> 1360.1002
B10: Add: Depreciation | F10: ='Income Statement'!F12 -> 151.53313 | G10: ='Income Statement'!G12 -> 179.55514 | H10: ='Income Statement'!H12 -> 212.23859 | I10: ='Income Statement'!I12 -> 250.37073 | J10: ='Income Statement'!J12 -> 294.87316
B11: Add Amortization | F11: ='Income Statement'!F13 -> 13.295973 | G11: ='Income Statement'!G13 -> 17.13899 | H11: ='Income Statement'!H13 -> 21.621292 | I11: ='Income Statement'!I13 -> 26.850843 | J11: ='Income Statement'!J13 -> 32.954034
B12: Less: Capex | F12: =-'Depreciation Capex Forecast'!F18 -> -288.39762 | G12: =-'Depreciation Capex Forecast'!G18 -> -336.26403 | H12: =-'Depreciation Capex Forecast'!H18 -> -392.20141 | I12: =-'Depreciation Capex Forecast'!I18 -> -457.58571 | J12: =-'Depreciation Capex Forecast'!J18 -> -534.02919
B13: Less: Addition to Intangibles | F13: ='Cash Flow Statement'!F23 -> -32.959728 | G13: ='Cash Flow Statement'!G23 -> -38.430174 | H13: ='Cash Flow Statement'!H23 -> -44.823018 | I13: ='Cash Flow Statement'!I23 -> -52.295509 | J13: ='Cash Flow Statement'!J23 -> -61.031907
B14: Add: Change in working capital | F14: =SUM('Cash Flow Statement'!F10:F15) -> 31.148562 | G14: =SUM('Cash Flow Statement'!G10:G15) -> -61.73698 | H14: =SUM('Cash Flow Statement'!H10:H15) -> -72.152599 | I14: =SUM('Cash Flow Statement'!I10:I15) -> -84.344136 | J14: =SUM('Cash Flow Statement'!J10:J15) -> -98.616588
B15: FCFF | F15: =SUM(F9:F14) -> 616.4105 | G15: =SUM(G9:G14) -> 622.40453 | H15: =SUM(H9:H14) -> 727.57058 | I15: =SUM(I9:I14) -> 850.50919 | J15: =SUM(J9:J14) -> 994.24972
B18: WACC (Weighted Average Cost of Capital) | C18: ='Cost of Capital Calculation'!G37 -> 0.057541669
B19: Infinite growth rate | C19: 0.01
B21: Free Cash Flow to Firm of Explicit Period
B22: (Year 1 to Year 5) | F22: =F4 -> Forecast 1 | G22: =G4 -> Forecast 2 | H22: =H4 -> Forecast 3 | I22: =I4 -> Forecast 4 | J22: =J4 -> Forecast 5
B23: Cash Flows | F23: =F15 -> 616.4105 | G23: =G15 -> 622.40453 | H23: =H15 -> 727.57058 | I23: =I15 -> 850.50919 | J23: =J15 -> 994.24972
B24: NPV of explicit period | C24: =NPV(C18,F23:J23) -> 3186.1453
B26: Terminal value | F26: =F22 -> Forecast 1 | G26: =G22 -> Forecast 2 | H26: =H22 -> Forecast 3 | I26: =I22 -> Forecast 4 | J26: =J22 -> Forecast 5
B27: Terminal value (at the end of 5th year) | F27: 0 | G27: 0 | H27: 0 | I27: 0 | J27: =J23*((1+C19)/(C18-C19)) -> 21122.359
B28: NPV of terminal value | C28: =NPV(C18,F27:J27) -> 15968.164
B30: DCF calculation as of | C30: Historical data | D30: End of the Year Target Price | E30: End of the Year Target Price
B31: NPV of explicit period | C31: =C24 -> 3186.1453 | D31: =NPV(C18,G23:J23) -> 2753.0709 | E31: =NPV(C18,H23:J23) -> 2289.0827
B32: NPV of terminal value | C32: =C28 -> 15968.164 | D32: =NPV(C18,G27:J27) -> 16886.999 | E32: =NPV(D18,H27:J27) -> 21122.359
B33: Enterprise Value | C33: =SUM(C31:C32) -> 19154.309 | D33: =SUM(D31:D32) -> 19640.07 | E33: =SUM(E31:E32) -> 23411.442
B34: + Cash | C34: ='Balance Sheet'!E7 -> 48.713267 | D34: ='Balance Sheet'!F7 -> 30 | E34: ='Balance Sheet'!G7 -> -1.3209401
B35: - Debt | C35: ='Balance Sheet'!E38 -> 1736 | D35: ='Balance Sheet'!F38 -> 1485.4693 | E35: ='Balance Sheet'!G38 -> 1273.1813
B36: Equity value | C36: =C33+C34-C35 -> 17467.023 | D36: =D33+D34-D35 -> 18184.601 | E36: =E33+E34-E35 -> 22136.94
B37: + Marketable Securities / Long Term Securities | C37: ='Balance Sheet'!E14+'Balance Sheet'!E8 -> 260 | D37: ='Balance Sheet'!F14+'Balance Sheet'!F8 -> 290 | E37: ='Balance Sheet'!G14+'Balance Sheet'!G8 -> 320
B38: Adjusted Equity Value | C38: =C36+C37 -> 17727.023 | D38: =D36+D37 -> 18474.601 | E38: =E36+E37 -> 22456.94
B39: Number of Shares | C39: ='Income Statement'!E24 -> 96.61569 | D39: ='Income Statement'!F24 -> 94.909212 | E39: ='Income Statement'!G24 -> 93.490005
B41: Share Price | C41: =C38/C39 -> 183.47975 | D41: =D38/D39 -> 194.6555 | E41: =E38/E39 -> 240.20685
D46: Sensitivity Analysis
E47: WACC
D48: =D41 -> 194.6555 | E48: =F48-1% -> 0.044 | F48: =G48-1% -> 0.054 | G48: 0.064 | H48: =G48+1% -> 0.074 | I48: =H48+1% -> 0.084
C49: growth | D49: 0.005 | E49: =TABLE($D$48,$C$19,$D49,$C$18,E$48) -> 244.96966 | F49: =TABLE($D$48,$C$19,$D49,$C$18,F$48) -> 191.08268 | G49: =TABLE($D$48,$C$19,$D49,$C$18,G$48) -> 155.49893 | H49: =TABLE($D$48,$C$19,$D49,$C$18,H$48) -> 130.25918 | I49: =TABLE($D$48,$C$19,$D49,$C$18,I$48) -> 111.43424
D50: 0.0075 | E50: =TABLE($D$48,$C$19,$D50,$C$18,E$48) -> 261.1381 | F50: =TABLE($D$48,$C$19,$D50,$C$18,F$48) -> 200.89917 | G50: =TABLE($D$48,$C$19,$D50,$C$18,G$48) -> 162.02125 | H50: =TABLE($D$48,$C$19,$D50,$C$18,H$48) -> 134.86645 | I50: =TABLE($D$48,$C$19,$D50,$C$18,I$48) -> 114.83637
D51: 0.01 | E51: =TABLE($D$48,$C$19,$D51,$C$18,E$48) -> 279.68425 | F51: =TABLE($D$48,$C$19,$D51,$C$18,F$48) -> 211.83117 | G51: =TABLE($D$48,$C$19,$D51,$C$18,G$48) -> 169.14748 | H51: =TABLE($D$48,$C$19,$D51,$C$18,H$48) -> 139.83366 | I51: =TABLE($D$48,$C$19,$D51,$C$18,I$48) -> 118.46837
D52: 0.0125 | E52: =TABLE($D$48,$C$19,$D52,$C$18,E$48) -> 301.17424 | F52: =TABLE($D$48,$C$19,$D52,$C$18,F$48) -> 224.08028 | G52: =TABLE($D$48,$C$19,$D52,$C$18,G$48) -> 176.96558 | H52: =TABLE($D$48,$C$19,$D52,$C$18,H$48) -> 145.20471 | I52: =TABLE($D$48,$C$19,$D52,$C$18,I$48) -> 122.35436
D53: 0.015 | E53: =TABLE($D$48,$C$19,$D53,$C$18,E$48) -> 326.3694 | F53: =TABLE($D$48,$C$19,$D53,$C$18,F$48) -> 237.89979 | G53: =TABLE($D$48,$C$19,$D53,$C$18,G$48) -> 185.58145 | H53: =TABLE($D$48,$C$19,$D53,$C$18,H$48) -> 151.03094 | I53: =TABLE($D$48,$C$19,$D53,$C$18,I$48) -> 126.52194
D54: 0.0175 | E54: =TABLE($D$48,$C$19,$D54,$C$18,E$48) -> 356.31836 | F54: =TABLE($D$48,$C$19,$D54,$C$18,F$48) -> 253.61238 | G54: =TABLE($D$48,$C$19,$D54,$C$18,G$48) -> 195.12375 | H54: =TABLE($D$48,$C$19,$D54,$C$18,H$48) -> 157.37275 | I54: =TABLE($D$48,$C$19,$D54,$C$18,I$48) -> 131.00288

Sheet Cost of Capital Calculation
A1: Big Books Company
B2: Cost of Capital Calculations
D4: E = Market Value of Equity
D5: V = Total market value of equity & debt
D6: Ke = Cost of Equity
D7: D = Market Value of Debt
D8: Kd = Cost of Debt
D9: Tax Rate = Corporate Tax Rate
B15: Step 1 - Find the Cost of Equity using CAPM Model
B17: Cost of Equity = Risk-Free Rate of Return + Beta * (Market Rate of Return – Risk-free Rate of Return)
B19: Risk-Free Rate of Return
B20: Visit - https://www.bankrate.com/rates/interest-rates/10-year-treasury-bill.aspx
B21: Take the rate of return mentioned in the table
B23: Risk-Free Rate of Return | C23: 0.0068
B25: Risk Premium (Market Rate of Return - Risk Free Rate of Return)
B26: Visit - http://pages.stern.nyu.edu/~adamodar/New_Home_Page/datafile/ctryprem.html
B27: take the Risk Premium of United States | C27: 0.0523
B29: Debt | C29: ='Balance Sheet'!E38 -> 1736 | F29: WACC of ABC company
B30: Equity | C30: ='Balance Sheet'!E47 -> 1419.4133 | F30: Risk Free rate | G30: =C23 -> 0.0068
B31: Total | C31: =SUM(C29:C30) -> 3155.4133 | F31: Market risk premium | G31: =C27 -> 0.0523
F32: Levered beta of ABC | G32: ='Beta Calculation'!H5 -> 1.7435235
F33: Cost of equity | G33: =G30+G32*G31 -> 0.097986277
B34: % Equity - Equity / (Debt + Equity) | C34: =C30/C31 -> 0.44983435 | F34: Pre-tax cost of debt | G34: =C39 -> 0.032902477
B35: % Debt - Debt/ (Debt + Equity) | C35: =C29/C31 -> 0.55016565 | F35: Tax rate | G35: ='Income Statement'!E23 -> 0.25620289
F36: After tax cost of debt | G36: =G34*(1-G35) -> 0.024472767
B37: Average Debt | C37: =AVERAGE('Balance Sheet'!D38:E38) -> 1938 | F37: WACC | G37: =(C34*G33)+(C35*G36) -> 0.057541669
B38: Interest expense | C38: ='Income Statement'!E16 -> 63.765
B39: Pre-tax Cost of Debt | C39: =C38/C37 -> 0.032902477

Sheet Beta Calculation
B1: S&P Index | C1: % change in S&P Index | D1: Big Books | E1: % change in Big Books
A2: Date | B2: Adj Close | D2: Adj Close
A3: 43047 | B3: 2594.3799 | D3: 110
A4: 43048 | B4: 2584.6201 | C4: =(B4-B3)/B3 -> -0.0037618878 | D4: 109.25678 | E4: =(D4-D3)/D3 -> -0.0067565585
A5: 43049 | B5: 2582.3 | C5: =(B5-B4)/B4 -> -0.00089764371 | D5: 109.07993 | E5: =(D5-D4)/D4 -> -0.001618671 | G5: SLOPE Method | H5: =SLOPE(E4:E713,C4:C713) -> 1.7435235
A6: 43052 | B6: 2584.8401 | C6: =(B6-B5)/B5 -> 0.00098363434 | D6: 109.25836 | E6: =(D6-D5)/D5 -> 0.0016357479
A7: 43053 | B7: 2578.8701 | C7: =(B7-B6)/B6 -> -0.0023096094 | D7: 108.792 | E7: =(D7-D6)/D6 -> -0.0042683598
A8: 43054 | B8: 2564.6201 | C8: =(B8-B7)/B7 -> -0.0055256757 | D8: 107.82215 | E8: =(D8-D7)/D7 -> -0.0089147418
A9: 43055 | B9: 2585.6399 | C9: =(B9-B8)/B8 -> 0.0081960583 | D9: 109.2919 | E9: =(D9-D8)/D8 -> 0.013631261 | G9: covariance(x,y) | H9: =_xlfn.COVARIANCE.P(C3:C713,E3:E713) -> 0.00037720083
A10: 43056 | B10: 2578.8501 | C10: =(B10-B9)/B9 -> -0.0026259631 | D10: 108.7995 | E10: =(D10-D9)/D9 -> -0.0045053852 | G10: variance(x) | H10: =_xlfn.VAR.P(C4:C713) -> 0.000216344
A11: 43059 | B11: 2582.1399 | C11: =(B11-B10)/B10 -> 0.0012756829 | D11: 109.0596 | E11: =(D11-D10)/D10 -> 0.0023906927 | G11: B | H11: =H9/H10 -> 1.7435235
A12: 43060 | B12: 2599.03 | C12: =(B12-B11)/B11 -> 0.006541139 | D12: 110.3496 | E12: =(D12-D11)/D11 -> 0.011828369
A13: 43061 | B13: 2597.0801 | C13: =(B13-B12)/B12 -> -0.00075026105 | D13: 110.19727 | E13: =(D13-D12)/D12 -> -0.0013804381
A14: 43063 | B14: 2602.4199 | C14: =(B14-B13)/B13 -> 0.0020560952 | D14: 110.62157 | E14: =(D14-D13)/D13 -> 0.0038503872
A15: 43066 | B15: 2601.4199 | C15: =(B15-B14)/B14 -> -0.00038425774 | D15: 110.54405 | E15: =(D15-D14)/D14 -> -0.00070081558
A16: 43067 | B16: 2627.04 | C16: =(B16-B15)/B15 -> 0.0098485126 | D16: 112.31 | E16: =(D16-D15)/D15 -> 0.015975061
A17: 43068 | B17: 2626.0701 | C17: =(B17-B16)/B16 -> -0.00036922582 | D17: 112.24052 | E17: =(D17-D16)/D16 -> -0.00061863833
A18: 43069 | B18: 2647.5801 | C18: =(B18-B17)/B17 -> 0.0081909505 | D18: 113.75081 | E18: =(D18-D17)/D17 -> 0.01345587
A19: 43070 | B19: 2642.22 | C19: =(B19-B18)/B18 -> -0.0020245306 | D19: 113.31556 | E19: =(D19-D18)/D18 -> -0.0038263089
A20: 43073 | B20: 2639.4399 | C20: =(B20-B19)/B19 -> -0.0010521569 | D20: 113.11512 | E20: =(D20-D19)/D19 -> -0.0017689465
A21: 43074 | B21: 2629.5701 | C21: =(B21-B20)/B20 -> -0.0037393815 | D21: 112.34014 | E21: =(D21-D20)/D20 -> -0.0068512428
A22: 43075 | B22: 2629.27 | C22: =(B22-B21)/B21 -> -0.00011410535 | D22: 112.31763 | E22: =(D22-D21)/D21 -> -0.00020031082
A23: 43076 | B23: 2636.98 | C23: =(B23-B22)/B22 -> 0.0029323576 | D23: 112.91525 | E23: =(D23-D22)/D22 -> 0.0053208056
... A713: 44078 | B713: 3426.96 | C713: =(B713-B712)/B712 -> -0.0081330274 | D713: 164.78129 | E713: =(D713-D712)/D712 -> -0.015133813
D715: =_xlfn.COVARIANCE.P(C4:C713,E4:E713)/_xlfn.VAR.P(C4:C713) -> 1.7435235
D716: =SLOPE(E4:E713,C4:C713) -> 1.7435235 | G716: BUY
